{"object_property":[{"object_id":0,"shape":"cube","size":"medium","material":"dirt","density":4,"mass":0.864,"friction":0.5,"restitution":0.3},{"object_id":1,"shape":"cube","size":"small","material":"metal","density":9,"mass":0.576,"friction":0.125,"restitution":0.6},{"object_id":2,"shape":"cube","size":"small","material":"wood","density":1,"mass":0.064,"friction":0.5,"restitution":0.9},{"object_id":3,"shape":"cube","size":"large","material":"concrete","density":9,"mass":4.608,"friction":0.5,"restitution":0.9}],"trajectory":[{"frame_id":0,"trajectory":[{"object_id":0,"location":[-1.43552,1.35849,0.3],"orientation":[-0.38836,0.0,0.0,0.71598],"velocity":[3.12573,-4.32254,0.0],"angular_velocity":[0.0,0.0,0.0]},{"object_id":1,"location":[0.58312,0.48715,0.2],"orientation":[0.71136,0.0,0.0,0.17589],"velocity":[-6.47856,-0.06634,0.0],"angular_velocity":[0.0,0.0,0.0]},{"object_id":2,"location":[-1.09284,-0.16553,0.2],"orientation":[-0.07502,0.0,0.0,0.73636],"velocity":[-3.98155,-0.38372,0.0],"angular_velocity":[0.0,0.0,0.0]},{"object_id":3,"location":[-0.39883,-1.14868,0.4],"orientation":[0.76211,0.0,0.0,-0.496],"velocity":[-1.99438,-0.14981,0.0],"angular_velocity":[0.0,0.0,0.0]}]},{"frame_id":1,"trajectory":[{"object_id":0,"location":[-1.33312,1.21689,0.3],"orientation":[-0.38836,0.0,-0.0,0.71598],"velocity":[3.02992,-4.19005,-0.0],"angular_velocity":[6e-05,-3e-05,-0.00017]},{"object_id":1,"location":[0.36794,0.48495,0.2],"orientation":[0.71137,0.0,0.0,0.17585],"velocity":[-6.4377,-0.06592,-0.0],"angular_velocity":[-6e-05,-0.00107,-1.44036]},{"object_id":2,"location":[-1.2225,-0.17803,0.2],"orientation":[-0.07502,-0.0,-0.0,0.73636],"velocity":[-3.81881,-0.36804,-0.0],"angular_velocity":[-2e-05,0.00015,-0.00243]},{"object_id":3,"location":[-0.46226,-1.15345,0.4],"orientation":[0.76211,0.0,-0.0,-0.496],"velocity":[-1.83158,-0.13759,-0.00049],"angular_velocity":[-0.026,0.17403,0.00437]}]},{"frame_id":2,"trajectory":[{"object_id":0,"location":[-1.23392,1.0797,0.3],"orientation":[-0.38836,0.0,0.0,0.71598],"velocity":[2.93412,-4.05756,-0.0],"angular_velocity":[-0.00307,-0.00417,-0.00047]},{"object_id":1,"location":[0.15411,0.48276,0.2],"orientation":[0.71153,-0.0,-0.0,0.1754],"velocity":[-6.39683,-0.0655,-0.0],"angular_velocity":[-5e-05,-0.00028,-3.78623]},{"object_id":2,"location":[-1.34674,-0.19,0.2],"orientation":[-0.07502,-0.0,0.0,0.73636],"velocity":[-3.65606,-0.35235,-1e-05],"angular_velocity":[-0.00136,0.00513,-0.00392]},{"object_id":3,"location":[-0.52024,-1.1578,0.4],"orientation":[0.76211,-0.0,-0.0,-0.49599],"velocity":[-1.66831,-0.12533,-3e-05],"angular_velocity":[0.01299,-0.01119,0.00928]}]},{"frame_id":3,"trajectory":[{"object_id":0,"location":[-1.13792,0.94694,0.3],"orientation":[-0.38836,0.0,-0.0,0.71598],"velocity":[2.83831,-3.92507,-0.0],"angular_velocity":[6e-05,-3e-05,-0.00069]},{"object_id":1,"location":[-0.05835,0.48059,0.2],"orientation":[0.71172,0.0,0.0,0.17488],"velocity":[-6.35595,-0.06508,-1e-05],"angular_velocity":[-0.00151,-0.00026,-3.74666]},{"object_id":2,"location":[-1.46556,-0.20145,0.2],"orientation":[-0.07502,0.0,-0.0,0.73636],"velocity":[-3.49331,-0.33667,-0.0],"angular_velocity":[-2e-05,-0.00051,-0.00626]},{"object_id":3,"location":[-0.5728,-1.16175,0.4],"orientation":[0.76211,0.0,-0.0,-0.49599],"velocity":[-1.50527,-0.11309,-2e-05],"angular_velocity":[-0.00662,0.00678,0.01355]}]},{"frame_id":4,"trajectory":[{"object_id":0,"location":[-1.0451,0.81859,0.3],"orientation":[-0.38836,-0.0,0.0,0.71598],"velocity":[2.7425,-3.79258,0.0],"angular_velocity":[0.00443,0.00117,-0.00092]},{"object_id":1,"location":[-0.26945,0.47843,0.2],"orientation":[0.71191,-0.0,-0.0,0.17436],"velocity":[-6.31507,-0.06466,-0.0],"angular_velocity":[-1e-05,7e-05,-3.70728]},{"object_id":2,"location":[-1.57895,-0.21238,0.2],"orientation":[-0.07502,0.0,0.0,0.73636],"velocity":[-3.33056,-0.32098,-0.0],"angular_velocity":[-3e-05,-0.00053,-0.00855]},{"object_id":3,"location":[-0.61991,-1.16529,0.4],"orientation":[0.76212,0.0,-0.0,-0.49599],"velocity":[-1.34222,-0.10085,-2e-05],"angular_velocity":[0.0086,-0.00859,0.01952]}]},{"frame_id":5,"trajectory":[{"object_id":0,"location":[-0.97082,0.69977,0.30147],"orientation":[-0.38001,0.00103,-0.00058,0.72202],"velocity":[-1.00771,-2.44583,0.33417],"angular_velocity":[-4.30976,46.81525,-429.89264]},{"object_id":1,"location":[-0.45587,0.46856,0.2007],"orientation":[0.70767,0.00088,0.0003,0.18565],"velocity":[-0.72871,-1.90237,0.16367],"angular_velocity":[36.91631,29.62727,670.02673]},{"object_id":2,"location":[-1.68692,-0.22279,0.2],"orientation":[-0.07502,0.0,0.0,0.73636],"velocity":[-3.16781,-0.3053,-0.0],"angular_velocity":[0.0004,-5e-05,-0.01032]},{"object_id":3,"location":[-0.6616,-1.16842,0.4],"orientation":[0.76212,-0.0,0.0,-0.49599],"velocity":[-1.17949,-0.08864,-0.00064],"angular_velocity":[0.24437,-0.61385,0.02541]}]},{"frame_id":6,"trajectory":[{"object_id":0,"location":[-1.00416,0.61855,0.30788],"orientation":[-0.30936,0.00541,-0.00457,0.76452],"velocity":[-0.99609,-2.42641,0.08451],"angular_velocity":[9.31869,13.19242,-417.81967]},{"object_id":1,"location":[-0.47993,0.40515,0.20245],"orientation":[0.66336,0.00269,0.00166,0.26919],"velocity":[-0.71971,-1.90083,-0.03305],"angular_velocity":[-4.7272,-8.34892,660.86328]},{"object_id":2,"location":[-1.74024,-0.2484,0.2],"orientation":[-0.05372,-0.0,-0.0,0.73893],"velocity":[1.6739,-1.76503,-0.0],"angular_velocity":[-7e-05,-0.0002,-421.02475]},{"object_id":3,"location":[-0.69785,-1.17115,0.4],"orientation":[0.76212,0.0,-0.0,-0.49598],"velocity":[-1.01613,-0.07639,-2e-05],"angular_velocity":[0.00223,-0.00037,0.03142]}]},{"frame_id":7,"trajectory":[{"object_id":0,"location":[-1.06057,0.5531,0.30568],"orientation":[-0.27367,-0.0042,0.00062,0.78129],"velocity":[-1.77894,-1.90739,-0.20466],"angular_velocity":[-3.24528,-54.085,-170.92238]},{"object_id":1,"location":[-0.4767,0.32522,0.21213],"orientation":[0.63845,0.011,0.00672,0.2997],"velocity":[0.19218,-2.45576,0.1854],"angular_velocity":[27.45243,51.01105,258.37881]},{"object_id":2,"location":[-1.68649,-0.30527,0.2],"orientation":[0.00882,-0.0,-0.0,0.74155],"velocity":[1.56527,-1.65902,-0.0],"angular_velocity":[9e-05,3e-05,-383.65054]},{"object_id":3,"location":[-0.72866,-1.17346,0.4],"orientation":[0.76213,0.0,-0.0,-0.49598],"velocity":[-0.8531,-0.06413,-3e-05],"angular_velocity":[0.0039,0.00609,0.03368]}]},{"frame_id":8,"trajectory":[{"object_id":0,"location":[-1.11655,0.4923,0.30203],"orientation":[-0.24464,-0.00224,-0.00081,0.79299],"velocity":[-1.63302,-1.78579,-0.12462],"angular_velocity":[-16.50183,18.63247,-148.11011]},{"object_id":1,"location":[-0.47027,0.24356,0.214],"orientation":[0.61492,0.01345,0.01127,0.32153],"velocity":[0.19322,-2.44405,-0.03476],"angular_velocity":[-21.17848,18.59544,259.9592]},{"object_id":2,"location":[-1.63626,-0.35846,0.2],"orientation":[0.06556,-0.0,-0.0,0.73761],"velocity":[1.46296,-1.54547,-0.0],"angular_velocity":[5e-05,-2e-05,-347.91608]},{"object_id":3,"location":[-0.75404,-1.17537,0.4],"orientation":[0.76213,-0.0,0.0,-0.49597],"velocity":[-0.69024,-0.05191,-0.00039],"angular_velocity":[0.16842,-0.38968,0.03634]}]},{"frame_id":9,"trajectory":[{"object_id":0,"location":[-1.16806,0.43534,0.3],"orientation":[-0.21842,-0.0,0.0,0.80219],"velocity":[-1.47325,-1.64526,-1e-05],"angular_velocity":[0.00065,0.00213,-127.38086]},{"object_id":1,"location":[-0.46384,0.16254,0.21079],"orientation":[0.33692,0.00935,0.00945,0.59312],"velocity":[0.19224,-2.42312,-0.17296],"angular_velocity":[-0.49181,-52.77192,262.97162]},{"object_id":2,"location":[-1.58929,-0.40778,0.2],"orientation":[0.11547,-0.0,-0.0,0.72899],"velocity":[1.36814,-1.42804,-0.0],"angular_velocity":[5e-05,-4e-05,-310.18851]},{"object_id":3,"location":[-0.77398,-1.17687,0.4],"orientation":[0.76213,0.0,-0.0,-0.49597],"velocity":[-0.52702,-0.03967,-2e-05],"angular_velocity":[0.01671,-0.01583,0.04233]}]},{"frame_id":10,"trajectory":[{"object_id":0,"location":[-1.21502,0.38244,0.3],"orientation":[-0.19501,-0.0,0.0,0.8094],"velocity":[-1.35877,-1.54144,0.0],"angular_velocity":[0.0021,-0.00901,-114.22696]},{"object_id":1,"location":[-0.45749,0.08204,0.20143],"orientation":[0.31906,0.00113,0.00135,0.61848],"velocity":[0.1894,-2.40869,-0.36585],"angular_velocity":[15.31773,-105.3151,264.35312]},{"object_id":2,"location":[-1.54534,-0.45315,0.2],"orientation":[0.15778,-0.0,-0.0,0.71755],"velocity":[1.2809,-1.30908,-0.0],"angular_velocity":[5e-05,2e-05,-269.64136]},{"object_id":3,"location":[-0.78849,-1.17796,0.4],"orientation":[0.76214,0.0,-0.0,-0.49596],"velocity":[-0.36407,-0.02744,-0.00022],"angular_velocity":[-0.01103,0.08017,0.0457]}]},{"frame_id":11,"trajectory":[{"object_id":0,"location":[-1.25817,0.33304,0.3],"orientation":[-0.17363,0.0,-0.0,0.81518],"velocity":[-1.24494,-1.43547,-5e-05],"angular_velocity":[0.00955,-0.00338,-103.16426]},{"object_id":1,"location":[-0.45126,0.00373,0.2],"orientation":[0.29698,0.0,0.0,0.6412],"velocity":[0.18682,-2.32765,-0.0],"angular_velocity":[-5e-05,1e-05,248.95103]},{"object_id":2,"location":[-1.5042,-0.49456,0.2],"orientation":[0.19234,-0.0,-0.0,0.70499],"velocity":[1.19855,-1.19013,-0.0],"angular_velocity":[-0.00049,-0.00113,-228.33075]},{"object_id":3,"location":[-0.79757,-1.17865,0.4],"orientation":[0.76214,0.0,-0.0,-0.49595],"velocity":[-0.20092,-0.01518,-1e-05],"angular_velocity":[0.00066,-0.00143,0.04409]}]},{"frame_id":12,"trajectory":[{"object_id":0,"location":[-1.29754,0.28721,0.3],"orientation":[-0.15401,0.0,-0.0,0.81984],"velocity":[-1.13178,-1.32717,-1e-05],"angular_velocity":[0.00447,-0.02338,-94.06662]},{"object_id":1,"location":[-0.44503,-0.07313,0.2],"orientation":[0.27186,-0.0,-0.0,0.66147],"velocity":[0.18656,-2.28876,-0.0],"angular_velocity":[-0.0,0.0,241.56795]},{"object_id":2,"location":[-1.46579,-0.53201,0.2],"orientation":[0.2198,0.0,-0.0,0.69261],"velocity":[1.11599,-1.072,-0.00037],"angular_velocity":[-0.13699,-0.15317,-190.06319]},{"object_id":3,"location":[-0.80122,-1.17892,0.4],"orientation":[0.76215,-0.0,-0.0,-0.49595],"velocity":[-0.0379,-0.00273,-1e-05],"angular_velocity":[0.00069,0.00166,-0.00083]}]},{"frame_id":13,"trajectory":[{"object_id":0,"location":[-1.33316,0.24504,0.3],"orientation":[-0.13584,-0.0,-0.0,0.82362],"velocity":[-1.01939,-1.21662,-0.0],"angular_velocity":[-0.00012,4e-05,-86.74999]},{"object_id":1,"location":[-0.43889,-0.1487,0.2],"orientation":[0.24435,0.0,-0.0,0.67937],"velocity":[0.18134,-2.25041,-0.0],"angular_velocity":[0.0,-0.00034,236.46935]},{"object_id":2,"location":[-1.43019,-0.56553,0.2],"orientation":[0.24128,0.0,-0.0,0.68115],"velocity":[1.03036,-0.95449,-0.0009],"angular_velocity":[-0.39577,-0.36578,-156.89296]},{"object_id":3,"location":[-0.80129,-1.17893,0.4],"orientation":[0.76215,0.0,0.0,-0.49595],"velocity":[-0.0001,-0.0,-6e-05],"angular_velocity":[0.00301,-0.00825,0.00018]}]},{"frame_id":14,"trajectory":[{"object_id":0,"location":[-1.36505,0.2066,0.3],"orientation":[-0.11885,-0.0,0.0,0.82671],"velocity":[-0.90817,-1.10352,-0.0],"angular_velocity":[-0.00015,3e-05,-81.04827]},{"object_id":1,"location":[-0.43294,-0.22298,0.2],"orientation":[0.21474,0.0,0.0,0.69507],"velocity":[0.17753,-2.21069,-0.0],"angular_velocity":[0.00016,-0.0002,234.06862]},{"object_id":2,"location":[-1.39755,-0.59515,0.2],"orientation":[0.25808,0.0,-0.0,0.6709],"velocity":[0.93881,-0.83772,-0.00096],"angular_velocity":[-0.39244,-0.39815,-130.07744]},{"object_id":3,"location":[-0.80129,-1.17893,0.4],"orientation":[0.76215,0.0,0.0,-0.49595],"velocity":[-9e-05,0.0,-5e-05],"angular_velocity":[0.00159,-0.00864,8e-05]}]},{"frame_id":15,"trajectory":[{"object_id":0,"location":[-1.39326,0.17198,0.3],"orientation":[-0.10276,0.0,0.0,0.82924],"velocity":[-0.7979,-0.98822,-1e-05],"angular_velocity":[0.00031,0.00079,-76.73444]},{"object_id":1,"location":[-0.42706,-0.29591,0.2],"orientation":[0.18333,-0.0,-0.0,0.70857],"velocity":[0.17618,-2.17027,-0.0],"angular_velocity":[7e-05,-0.00028,232.06947]},{"object_id":2,"location":[-1.36809,-0.62089,0.2],"orientation":[0.27136,-0.0,-0.0,0.66183],"velocity":[0.84067,-0.72198,-1e-05],"angular_velocity":[0.04242,0.06408,-109.19344]},{"object_id":3,"location":[-0.80129,-1.17893,0.4],"orientation":[0.76215,0.0,0.0,-0.49595],"velocity":[-9e-05,0.0,-6e-05],"angular_velocity":[0.00248,-0.0088,7e-05]}]},{"frame_id":16,"trajectory":[{"object_id":0,"location":[-1.4178,0.14123,0.3],"orientation":[-0.08734,-0.0,0.0,0.83131],"velocity":[-0.68877,-0.87062,-5e-05],"angular_velocity":[0.01232,-0.00761,-73.66622]},{"object_id":1,"location":[-0.42113,-0.3675,0.2],"orientation":[0.15075,0.0,0.0,0.71973],"velocity":[0.17887,-2.13015,-1e-05],"angular_velocity":[0.00026,-0.00173,227.75316]},{"object_id":2,"location":[-1.34199,-0.64282,0.2],"orientation":[0.28205,-0.0,-0.0,0.65378],"velocity":[0.73719,-0.60819,-5e-05],"angular_velocity":[0.031,0.06889,-93.37289]},{"object_id":3,"location":[-0.80129,-1.17893,0.4],"orientation":[0.76215,0.0,0.0,-0.49595],"velocity":[-9e-05,0.0,-5e-05],"angular_velocity":[0.00196,-0.00893,-0.00015]}]},{"frame_id":17,"trajectory":[{"object_id":0,"location":[-1.43873,0.11446,0.3],"orientation":[-0.07237,-0.0,0.0,0.833],"velocity":[-0.58097,-0.75044,-0.0],"angular_velocity":[-0.0002,1e-05,-71.72037]},{"object_id":1,"location":[-0.41512,-0.43776,0.2],"orientation":[0.11766,0.0,0.0,0.72849],"velocity":[0.18115,-2.09068,0.00014],"angular_velocity":[0.01087,-0.02068,221.96968]},{"object_id":2,"location":[-1.31944,-0.66099,0.2],"orientation":[0.29086,-0.0,-0.0,0.64658],"velocity":[0.62868,-0.49643,-1e-05],"angular_velocity":[0.0714,0.11217,-81.66633]},{"object_id":3,"location":[-0.80129,-1.17893,0.4],"orientation":[0.76215,0.0,0.0,-0.49595],"velocity":[-0.0001,-1e-05,-5e-05],"angular_velocity":[0.00253,-0.00829,0.00022]}]},{"frame_id":18,"trajectory":[{"object_id":0,"location":[-1.45612,0.09176,0.3],"orientation":[-0.05762,-0.0,0.0,0.83434],"velocity":[-0.47613,-0.62631,-0.0],"angular_velocity":[-0.00022,1e-05,-70.82919]},{"object_id":1,"location":[-0.40903,-0.50673,0.2],"orientation":[0.08447,0.0,0.0,0.73493],"velocity":[0.18363,-2.05228,-0.0],"angular_velocity":[-0.0,1e-05,216.18326]},{"object_id":2,"location":[-1.30058,-0.67547,0.2],"orientation":[0.29828,-0.0,0.0,0.64002],"velocity":[0.51581,-0.38698,-1e-05],"angular_velocity":[-0.00072,-0.00475,-73.08934]},{"object_id":3,"location":[-0.80129,-1.17893,0.4],"orientation":[0.76215,0.0,0.0,-0.49595],"velocity":[-8e-05,0.0,-6e-05],"angular_velocity":[0.00249,-0.00839,-2e-05]}]},{"frame_id":19,"trajectory":[{"object_id":0,"location":[-1.47013,0.07331,0.3],"orientation":[-0.04293,0.0,0.0,0.83537],"velocity":[-0.37921,-0.49505,-0.00014],"angular_velocity":[0.05177,-0.05661,-70.56123]},{"object_id":1,"location":[-0.38493,-0.50443,0.2],"orientation":[0.12043,0.0,0.0,0.72785],"velocity":[0.75179,0.16196,-0.0],"angular_velocity":[0.00012,-0.00021,-244.9702]},{"object_id":2,"location":[-1.28556,-0.68635,0.2],"orientation":[0.30469,-0.0,0.0,0.63393],"velocity":[0.39975,-0.27917,-3e-05],"angular_velocity":[0.00548,-0.01328,-66.83207]},{"object_id":3,"location":[-0.80298,-1.18522,0.4],"orientation":[0.76081,0.0,0.0,-0.49774],"velocity":[-0.0361,-0.13359,-1e-05],"angular_velocity":[-0.00034,0.00045,-5.19291]}]},{"frame_id":20,"trajectory":[{"object_id":0,"location":[-1.48132,0.05938,0.3],"orientation":[-0.02868,0.0,0.0,0.83609],"velocity":[-0.30585,-0.36292,-8e-05],"angular_velocity":[0.00303,0.02473,-64.09642]},{"object_id":1,"location":[-0.35993,-0.49892,0.2],"orientation":[0.15445,-0.0,0.0,0.7186],"velocity":[0.74922,0.16628,-0.0],"angular_velocity":[0.00066,-0.00173,-220.46899]},{"object_id":2,"location":[-1.27532,-0.69284,0.2],"orientation":[0.30985,-0.0,0.0,0.62871],"velocity":[-0.11703,0.22112,0.00118],"angular_velocity":[-0.23396,-0.09905,23.78229]},{"object_id":3,"location":[-0.80341,-1.18685,0.4],"orientation":[0.76059,0.0,-0.0,-0.49803],"velocity":[-3e-05,-0.00071,-0.00032],"angular_velocity":[-0.00068,-0.02837,-0.01991]}]},{"frame_id":21,"trajectory":[{"object_id":0,"location":[-1.49022,0.04921,0.3],"orientation":[-0.01728,0.0,-0.0,0.83645],"velocity":[-0.23563,-0.26079,-0.0001],"angular_velocity":[-0.019,-0.00329,-47.46549]},{"object_id":1,"location":[-0.33522,-0.49348,0.2],"orientation":[0.18405,0.0,-0.0,0.70829],"velocity":[0.72839,0.16052,-0.0],"angular_velocity":[0.00054,0.00041,-203.18124]},{"object_id":2,"location":[-1.27807,-0.6881,0.2],"orientation":[0.30867,0.0,0.0,0.62994],"velocity":[-0.05234,0.08072,-1e-05],"angular_velocity":[0.00209,-0.00104,7.06372]},{"object_id":3,"location":[-0.80341,-1.18685,0.4],"orientation":[0.76059,0.0,0.0,-0.49803],"velocity":[-0.0,2e-05,-7e-05],"angular_velocity":[0.00248,-0.00659,-0.00037]}]},{"frame_id":22,"trajectory":[{"object_id":0,"location":[-1.49661,0.04231,0.3],"orientation":[-0.00934,-0.0,-0.0,0.8366],"velocity":[-0.15686,-0.16592,-3e-05],"angular_velocity":[-0.0122,0.01256,-30.8568]},{"object_id":1,"location":[-0.31143,-0.48828,0.2],"orientation":[0.21039,-0.0,-0.0,0.69712],"velocity":[0.70757,0.15019,-0.0],"angular_velocity":[0.00062,3e-05,-186.39905]},{"object_id":2,"location":[-1.27853,-0.68745,0.2],"orientation":[0.30852,-0.0,0.0,0.63009],"velocity":[-2e-05,6e-05,-5e-05],"angular_velocity":[-0.00735,-0.01267,0.00021]},{"object_id":3,"location":[-0.80341,-1.18685,0.4],"orientation":[0.76059,0.0,0.0,-0.49803],"velocity":[-3e-05,1e-05,-7e-05],"angular_velocity":[0.00218,-0.00444,-0.00029]}]},{"frame_id":23,"trajectory":[{"object_id":0,"location":[-1.50028,0.03848,0.3],"orientation":[-0.00486,-0.0,-0.0,0.83664],"velocity":[-0.07345,-0.07547,-5e-05],"angular_velocity":[-0.01605,0.00669,-14.24351]},{"object_id":1,"location":[-0.28825,-0.48345,0.2],"orientation":[0.23324,-0.0,-0.0,0.68564],"velocity":[0.68561,0.14043,-0.0],"angular_velocity":[0.00041,3e-05,-171.26772]},{"object_id":2,"location":[-1.27853,-0.68745,0.2],"orientation":[0.30852,-0.0,-0.0,0.63009],"velocity":[-3e-05,6e-05,-5e-05],"angular_velocity":[-0.00746,-0.0135,-0.00026]},{"object_id":3,"location":[-0.80341,-1.18685,0.4],"orientation":[0.76059,0.0,0.0,-0.49803],"velocity":[1e-05,2e-05,-8e-05],"angular_velocity":[0.00223,-0.00566,-0.00055]}]},{"frame_id":24,"trajectory":[{"object_id":0,"location":[-1.50118,0.03756,0.3],"orientation":[-0.00377,0.0,-0.0,0.83665],"velocity":[-0.0001,-7e-05,-5e-05],"angular_velocity":[0.01204,-0.00974,-0.00071]},{"object_id":1,"location":[-0.26584,-0.47893,0.2],"orientation":[0.25292,0.0,-0.0,0.67419],"velocity":[0.66189,0.13205,-1e-05],"angular_velocity":[0.00184,0.00077,-154.86513]},{"object_id":2,"location":[-1.27853,-0.68745,0.2],"orientation":[0.30852,-0.0,-0.0,0.63009],"velocity":[-2e-05,6e-05,-5e-05],"angular_velocity":[-0.00762,-0.01293,-0.00013]},{"object_id":3,"location":[-0.80341,-1.18685,0.4],"orientation":[0.76059,0.0,0.0,-0.49803],"velocity":[-2e-05,1e-05,-8e-05],"angular_velocity":[0.00337,-0.00703,-0.00034]}]},{"frame_id":25,"trajectory":[{"object_id":0,"location":[-1.50118,0.03756,0.3],"orientation":[-0.00377,0.0,-0.0,0.83665],"velocity":[-2e-05,-3e-05,-5e-05],"angular_velocity":[0.00904,-0.00029,0.00014]},{"object_id":1,"location":[-0.24408,-0.47484,0.2],"orientation":[0.26946,-0.0,0.0,0.66318],"velocity":[0.6448,0.1153,-1e-05],"angular_velocity":[0.00162,0.00254,-137.20747]},{"object_id":2,"location":[-1.27853,-0.68745,0.2],"orientation":[0.30852,-0.0,-0.0,0.63009],"velocity":[-3e-05,6e-05,-5e-05],"angular_velocity":[-0.00627,-0.01441,-0.00021]},{"object_id":3,"location":[-0.80341,-1.18685,0.4],"orientation":[0.76059,0.0,0.0,-0.49803],"velocity":[-0.0,2e-05,-7e-05],"angular_velocity":[0.00252,-0.00673,-0.00037]}]},{"frame_id":26,"trajectory":[{"object_id":0,"location":[-1.50118,0.03756,0.3],"orientation":[-0.00377,0.0,-0.0,0.83665],"velocity":[-3e-05,-2e-05,-7e-05],"angular_velocity":[0.00842,-0.00319,0.00016]},{"object_id":1,"location":[-0.22297,-0.47131,0.2],"orientation":[0.28317,0.0,-0.0,0.65291],"velocity":[0.62422,0.09882,-1e-05],"angular_velocity":[0.00184,0.00048,-120.76659]},{"object_id":2,"location":[-1.27853,-0.68745,0.2],"orientation":[0.30852,-0.0,-0.0,0.63009],"velocity":[-1e-05,7e-05,-5e-05],"angular_velocity":[-0.00733,-0.01163,-0.0001]},{"object_id":3,"location":[-0.80341,-1.18685,0.4],"orientation":[0.76059,0.0,0.0,-0.49803],"velocity":[-2e-05,1e-05,-8e-05],"angular_velocity":[0.00341,-0.00558,-0.00019]}]},{"frame_id":27,"trajectory":[{"object_id":0,"location":[-1.50118,0.03756,0.3],"orientation":[-0.00377,0.0,-0.0,0.83665],"velocity":[-2e-05,-2e-05,-6e-05],"angular_velocity":[0.00778,-0.00189,0.00033]},{"object_id":1,"location":[-0.2026,-0.46832,0.2],"orientation":[0.29443,0.0,-0.0,0.64348],"velocity":[0.60021,0.08303,-0.0],"angular_velocity":[0.00103,0.00035,-105.67847]},{"object_id":2,"location":[-1.27853,-0.68745,0.2],"orientation":[0.30852,-0.0,-0.0,0.63009],"velocity":[-1e-05,6e-05,-7e-05],"angular_velocity":[-0.00491,-0.01482,-0.00024]},{"object_id":3,"location":[-0.80341,-1.18685,0.4],"orientation":[0.76059,0.0,0.0,-0.49803],"velocity":[-1e-05,2e-05,-7e-05],"angular_velocity":[0.00245,-0.00362,-0.00016]}]},{"frame_id":28,"trajectory":[{"object_id":0,"location":[-1.50118,0.03756,0.3],"orientation":[-0.00377,0.0,-0.0,0.83665],"velocity":[-2e-05,-3e-05,-5e-05],"angular_velocity":[0.00906,-0.00071,-0.00016]},{"object_id":1,"location":[-0.18309,-0.46583,0.2],"orientation":[0.30363,0.0,-0.0,0.63498],"velocity":[0.57313,0.06823,-0.0],"angular_velocity":[5e-05,4e-05,-91.94987]},{"object_id":2,"location":[-1.27853,-0.68745,0.2],"orientation":[0.30852,-0.0,-0.0,0.63009],"velocity":[-1e-05,6e-05,-5e-05],"angular_velocity":[-0.00731,-0.01118,0.00084]},{"object_id":3,"location":[-0.80341,-1.18685,0.4],"orientation":[0.76059,0.0,0.0,-0.49803],"velocity":[-2e-05,1e-05,-8e-05],"angular_velocity":[0.00337,-0.00703,-0.00034]}]},{"frame_id":29,"trajectory":[{"object_id":0,"location":[-1.50118,0.03756,0.3],"orientation":[-0.00377,0.0,-0.0,0.83665],"velocity":[-2e-05,-3e-05,-6e-05],"angular_velocity":[0.00809,-0.0026,0.00012]},{"object_id":1,"location":[-0.16454,-0.46381,0.2],"orientation":[0.31111,-0.0,-0.0,0.62738],"velocity":[0.54321,0.0549,-0.0],"angular_velocity":[0.00016,0.00014,-79.65835]},{"object_id":2,"location":[-1.27853,-0.68745,0.2],"orientation":[0.30852,-0.0,0.0,0.63009],"velocity":[-1e-05,6e-05,-5e-05],"angular_velocity":[-0.00683,-0.0117,0.00092]},{"object_id":3,"location":[-0.80341,-1.18685,0.4],"orientation":[0.76059,0.0,0.0,-0.49803],"velocity":[-0.0,2e-05,-7e-05],"angular_velocity":[0.00252,-0.00673,-0.00037]}]},{"frame_id":30,"trajectory":[{"object_id":0,"location":[-1.50118,0.03756,0.3],"orientation":[-0.00377,0.0,-0.0,0.83665],"velocity":[-2e-05,-3e-05,-6e-05],"angular_velocity":[0.00888,-0.00116,8e-05]},{"object_id":1,"location":[-0.14703,-0.4622,0.2],"orientation":[0.31718,0.0,-0.0,0.62069],"velocity":[0.51104,0.04306,-0.0],"angular_velocity":[0.00033,-8e-05,-68.62655]},{"object_id":2,"location":[-1.27853,-0.68745,0.2],"orientation":[0.30852,-0.0,-0.0,0.63009],"velocity":[-3e-05,6e-05,-5e-05],"angular_velocity":[-0.00712,-0.01351,-0.00028]},{"object_id":3,"location":[-0.80341,-1.18685,0.4],"orientation":[0.76059,0.0,0.0,-0.49803],"velocity":[-2e-05,1e-05,-8e-05],"angular_velocity":[0.00341,-0.00558,-0.00019]}]},{"frame_id":31,"trajectory":[{"object_id":0,"location":[-1.50118,0.03756,0.3],"orientation":[-0.00377,0.0,-0.0,0.83665],"velocity":[-3e-05,-2e-05,-6e-05],"angular_velocity":[0.00794,-0.00298,-0.00015]},{"object_id":1,"location":[-0.13063,-0.46097,0.2],"orientation":[0.32208,0.0,-0.0,0.61483],"velocity":[0.47703,0.0328,-1e-05],"angular_velocity":[0.00086,0.00101,-58.76559]},{"object_id":2,"location":[-1.27853,-0.68745,0.2],"orientation":[0.30852,-0.0,-0.0,0.63009],"velocity":[-1e-05,6e-05,-5e-05],"angular_velocity":[-0.00689,-0.01144,-3e-05]},{"object_id":3,"location":[-0.80341,-1.18685,0.4],"orientation":[0.76059,0.0,0.0,-0.49803],"velocity":[-1e-05,2e-05,-7e-05],"angular_velocity":[0.00245,-0.00362,-0.00016]}]},{"frame_id":32,"trajectory":[{"object_id":0,"location":[-1.50118,0.03756,0.3],"orientation":[-0.00377,0.0,-0.0,0.83665],"velocity":[-3e-05,-2e-05,-6e-05],"angular_velocity":[0.00794,-0.00298,-0.00015]},{"object_id":1,"location":[-0.11539,-0.46004,0.2],"orientation":[0.32603,0.0,0.0,0.60977],"velocity":[0.44157,0.02401,-0.0],"angular_velocity":[0.00018,-8e-05,-49.92519]},{"object_id":2,"location":[-1.27853,-0.68745,0.2],"orientation":[0.30852,-0.0,-0.0,0.63009],"velocity":[-1e-05,6e-05,-5e-05],"angular_velocity":[-0.00689,-0.01144,-3e-05]},{"object_id":3,"location":[-0.80341,-1.18685,0.4],"orientation":[0.76059,0.0,0.0,-0.49803],"velocity":[-1e-05,2e-05,-7e-05],"angular_velocity":[0.00245,-0.00362,-0.00016]}]},{"frame_id":33,"trajectory":[{"object_id":0,"location":[-1.50118,0.03756,0.3],"orientation":[-0.00377,0.0,-0.0,0.83665],"velocity":[-3e-05,-2e-05,-6e-05],"angular_velocity":[0.00794,-0.00298,-0.00015]},{"object_id":1,"location":[-0.10136,-0.45938,0.2],"orientation":[0.3292,0.0,-0.0,0.60545],"velocity":[0.40497,0.01664,-1e-05],"angular_velocity":[0.00098,0.00065,-42.01033]},{"object_id":2,"location":[-1.27853,-0.68745,0.2],"orientation":[0.30852,-0.0,-0.0,0.63009],"velocity":[-1e-05,6e-05,-5e-05],"angular_velocity":[-0.00689,-0.01144,-3e-05]},{"object_id":3,"location":[-0.80341,-1.18685,0.4],"orientation":[0.76059,0.0,0.0,-0.49803],"velocity":[-1e-05,2e-05,-7e-05],"angular_velocity":[0.00245,-0.00362,-0.00016]}]},{"frame_id":34,"trajectory":[{"object_id":0,"location":[-1.50118,0.03756,0.3],"orientation":[-0.00377,0.0,-0.0,0.83665],"velocity":[-3e-05,-2e-05,-6e-05],"angular_velocity":[0.00794,-0.00298,-0.00015]},{"object_id":1,"location":[-0.08856,-0.45895,0.2],"orientation":[0.33172,0.0,0.0,0.60181],"velocity":[0.36747,0.01055,-1e-05],"angular_velocity":[0.00188,-0.0004,-34.90902]},{"object_id":2,"location":[-1.27853,-0.68745,0.2],"orientation":[0.30852,-0.0,-0.0,0.63009],"velocity":[-1e-05,6e-05,-5e-05],"angular_velocity":[-0.00689,-0.01144,-3e-05]},{"object_id":3,"location":[-0.80341,-1.18685,0.4],"orientation":[0.76059,0.0,0.0,-0.49803],"velocity":[-1e-05,2e-05,-7e-05],"angular_velocity":[0.00245,-0.00362,-0.00016]}]},{"frame_id":35,"trajectory":[{"object_id":0,"location":[-1.50118,0.03756,0.3],"orientation":[-0.00377,0.0,-0.0,0.83665],"velocity":[-3e-05,-2e-05,-6e-05],"angular_velocity":[0.00794,-0.00298,-0.00015]},{"object_id":1,"location":[-0.07702,-0.45869,0.2],"orientation":[0.33371,-0.0,0.0,0.59878],"velocity":[0.32927,0.00564,-1e-05],"angular_velocity":[0.00079,0.00056,-28.54966]},{"object_id":2,"location":[-1.27853,-0.68745,0.2],"orientation":[0.30852,-0.0,-0.0,0.63009],"velocity":[-1e-05,6e-05,-5e-05],"angular_velocity":[-0.00689,-0.01144,-3e-05]},{"object_id":3,"location":[-0.80341,-1.18685,0.4],"orientation":[0.76059,0.0,0.0,-0.49803],"velocity":[-1e-05,2e-05,-7e-05],"angular_velocity":[0.00245,-0.00362,-0.00016]}]},{"frame_id":36,"trajectory":[{"object_id":0,"location":[-1.50118,0.03756,0.3],"orientation":[-0.00377,0.0,-0.0,0.83665],"velocity":[-3e-05,-2e-05,-6e-05],"angular_velocity":[0.00794,-0.00298,-0.00015]},{"object_id":1,"location":[-0.06677,-0.45858,0.2],"orientation":[0.33526,-0.0,-0.0,0.59633],"velocity":[0.29049,0.00181,-1e-05],"angular_velocity":[0.00134,0.00077,-22.87544]},{"object_id":2,"location":[-1.27853,-0.68745,0.2],"orientation":[0.30852,-0.0,-0.0,0.63009],"velocity":[-1e-05,6e-05,-5e-05],"angular_velocity":[-0.00689,-0.01144,-3e-05]},{"object_id":3,"location":[-0.80341,-1.18685,0.4],"orientation":[0.76059,0.0,0.0,-0.49803],"velocity":[-1e-05,2e-05,-7e-05],"angular_velocity":[0.00245,-0.00362,-0.00016]}]},{"frame_id":37,"trajectory":[{"object_id":0,"location":[-1.50118,0.03756,0.3],"orientation":[-0.00377,0.0,-0.0,0.83665],"velocity":[-3e-05,-2e-05,-6e-05],"angular_velocity":[0.00794,-0.00298,-0.00015]},{"object_id":1,"location":[-0.05783,-0.45857,0.2],"orientation":[0.33644,-0.0,-0.0,0.59438],"velocity":[0.25125,-0.00101,-1e-05],"angular_velocity":[0.00105,0.00067,-17.83862]},{"object_id":2,"location":[-1.27853,-0.68745,0.2],"orientation":[0.30852,-0.0,-0.0,0.63009],"velocity":[-1e-05,6e-05,-5e-05],"angular_velocity":[-0.00689,-0.01144,-3e-05]},{"object_id":3,"location":[-0.80341,-1.18685,0.4],"orientation":[0.76059,0.0,0.0,-0.49803],"velocity":[-1e-05,2e-05,-7e-05],"angular_velocity":[0.00245,-0.00362,-0.00016]}]},{"frame_id":38,"trajectory":[{"object_id":0,"location":[-1.50118,0.03756,0.3],"orientation":[-0.00377,0.0,-0.0,0.83665],"velocity":[-3e-05,-2e-05,-6e-05],"angular_velocity":[0.00794,-0.00298,-0.00015]},{"object_id":1,"location":[-0.05019,-0.45865,0.2],"orientation":[0.33733,0.0,0.0,0.59288],"velocity":[0.21164,-0.00293,-1e-05],"angular_velocity":[-0.0004,-0.00198,-13.40509]},{"object_id":2,"location":[-1.27853,-0.68745,0.2],"orientation":[0.30852,-0.0,-0.0,0.63009],"velocity":[-1e-05,6e-05,-5e-05],"angular_velocity":[-0.00689,-0.01144,-3e-05]},{"object_id":3,"location":[-0.80341,-1.18685,0.4],"orientation":[0.76059,0.0,0.0,-0.49803],"velocity":[-1e-05,2e-05,-7e-05],"angular_velocity":[0.00245,-0.00362,-0.00016]}]},{"frame_id":39,"trajectory":[{"object_id":0,"location":[-1.50118,0.03756,0.3],"orientation":[-0.00377,0.0,-0.0,0.83665],"velocity":[-3e-05,-2e-05,-6e-05],"angular_velocity":[0.00794,-0.00298,-0.00015]},{"object_id":1,"location":[-0.04389,-0.45877,0.2],"orientation":[0.33796,-0.0,0.0,0.59179],"velocity":[0.17172,-0.00399,-1e-05],"angular_velocity":[-0.00078,-0.00084,-9.55409]},{"object_id":2,"location":[-1.27853,-0.68745,0.2],"orientation":[0.30852,-0.0,-0.0,0.63009],"velocity":[-1e-05,6e-05,-5e-05],"angular_velocity":[-0.00689,-0.01144,-3e-05]},{"object_id":3,"location":[-0.80341,-1.18685,0.4],"orientation":[0.76059,0.0,0.0,-0.49803],"velocity":[-1e-05,2e-05,-7e-05],"angular_velocity":[0.00245,-0.00362,-0.00016]}]},{"frame_id":40,"trajectory":[{"object_id":0,"location":[-1.50118,0.03756,0.3],"orientation":[-0.00377,0.0,-0.0,0.83665],"velocity":[-3e-05,-2e-05,-6e-05],"angular_velocity":[0.00794,-0.00298,-0.00015]},{"object_id":1,"location":[-0.03891,-0.45891,0.2],"orientation":[0.59218,0.0,-0.0,0.33773],"velocity":[0.13154,-0.00423,-1e-05],"angular_velocity":[-0.00041,-0.00203,-6.27549]},{"object_id":2,"location":[-1.27853,-0.68745,0.2],"orientation":[0.30852,-0.0,-0.0,0.63009],"velocity":[-1e-05,6e-05,-5e-05],"angular_velocity":[-0.00689,-0.01144,-3e-05]},{"object_id":3,"location":[-0.80341,-1.18685,0.4],"orientation":[0.76059,0.0,0.0,-0.49803],"velocity":[-1e-05,2e-05,-7e-05],"angular_velocity":[0.00245,-0.00362,-0.00016]}]},{"frame_id":41,"trajectory":[{"object_id":0,"location":[-1.50118,0.03756,0.3],"orientation":[-0.00377,0.0,-0.0,0.83665],"velocity":[-3e-05,-2e-05,-6e-05],"angular_velocity":[0.00794,-0.00298,-0.00015]},{"object_id":1,"location":[-0.03529,-0.45904,0.2],"orientation":[0.59264,0.0,-0.0,0.33747],"velocity":[0.09116,-0.00373,-1e-05],"angular_velocity":[-0.0005,-0.00243,-3.56841]},{"object_id":2,"location":[-1.27853,-0.68745,0.2],"orientation":[0.30852,-0.0,-0.0,0.63009],"velocity":[-1e-05,6e-05,-5e-05],"angular_velocity":[-0.00689,-0.01144,-3e-05]},{"object_id":3,"location":[-0.80341,-1.18685,0.4],"orientation":[0.76059,0.0,0.0,-0.49803],"velocity":[-1e-05,2e-05,-7e-05],"angular_velocity":[0.00245,-0.00362,-0.00016]}]},{"frame_id":42,"trajectory":[{"object_id":0,"location":[-1.50118,0.03756,0.3],"orientation":[-0.00377,0.0,-0.0,0.83665],"velocity":[-3e-05,-2e-05,-6e-05],"angular_velocity":[0.00794,-0.00298,-0.00015]},{"object_id":1,"location":[-0.03301,-0.45914,0.2],"orientation":[0.59286,-0.0,-0.0,0.33734],"velocity":[0.05061,-0.00252,-1e-05],"angular_velocity":[-0.0005,-0.00266,-1.4807]},{"object_id":2,"location":[-1.27853,-0.68745,0.2],"orientation":[0.30852,-0.0,-0.0,0.63009],"velocity":[-1e-05,6e-05,-5e-05],"angular_velocity":[-0.00689,-0.01144,-3e-05]},{"object_id":3,"location":[-0.80341,-1.18685,0.4],"orientation":[0.76059,0.0,0.0,-0.49803],"velocity":[-1e-05,2e-05,-7e-05],"angular_velocity":[0.00245,-0.00362,-0.00016]}]},{"frame_id":43,"trajectory":[{"object_id":0,"location":[-1.50118,0.03756,0.3],"orientation":[-0.00377,0.0,-0.0,0.83665],"velocity":[-3e-05,-2e-05,-6e-05],"angular_velocity":[0.00794,-0.00298,-0.00015]},{"object_id":1,"location":[-0.03208,-0.45919,0.2],"orientation":[0.59292,0.0,-0.0,0.3373],"velocity":[0.00991,-0.00054,-1e-05],"angular_velocity":[-0.00123,-0.00315,-0.14542]},{"object_id":2,"location":[-1.27853,-0.68745,0.2],"orientation":[0.30852,-0.0,-0.0,0.63009],"velocity":[-1e-05,6e-05,-5e-05],"angular_velocity":[-0.00689,-0.01144,-3e-05]},{"object_id":3,"location":[-0.80341,-1.18685,0.4],"orientation":[0.76059,0.0,0.0,-0.49803],"velocity":[-1e-05,2e-05,-7e-05],"angular_velocity":[0.00245,-0.00362,-0.00016]}]},{"frame_id":44,"trajectory":[{"object_id":0,"location":[-1.50118,0.03756,0.3],"orientation":[-0.00377,0.0,-0.0,0.83665],"velocity":[-3e-05,-2e-05,-6e-05],"angular_velocity":[0.00794,-0.00298,-0.00015]},{"object_id":1,"location":[-0.03206,-0.4592,0.2],"orientation":[0.59292,-0.0,-0.0,0.3373],"velocity":[-0.00011,-0.00015,-2e-05],"angular_velocity":[0.02492,-0.02227,0.00044]},{"object_id":2,"location":[-1.27853,-0.68745,0.2],"orientation":[0.30852,-0.0,-0.0,0.63009],"velocity":[-1e-05,6e-05,-5e-05],"angular_velocity":[-0.00689,-0.01144,-3e-05]},{"object_id":3,"location":[-0.80341,-1.18685,0.4],"orientation":[0.76059,0.0,0.0,-0.49803],"velocity":[-1e-05,2e-05,-7e-05],"angular_velocity":[0.00245,-0.00362,-0.00016]}]},{"frame_id":45,"trajectory":[{"object_id":0,"location":[-1.50118,0.03756,0.3],"orientation":[-0.00377,0.0,-0.0,0.83665],"velocity":[-3e-05,-2e-05,-6e-05],"angular_velocity":[0.00794,-0.00298,-0.00015]},{"object_id":1,"location":[-0.03206,-0.4592,0.2],"orientation":[0.59292,-0.0,-0.0,0.3373],"velocity":[-0.00011,-0.00014,-2e-05],"angular_velocity":[0.0245,-0.02215,0.0004]},{"object_id":2,"location":[-1.27853,-0.68745,0.2],"orientation":[0.30852,-0.0,-0.0,0.63009],"velocity":[-1e-05,6e-05,-5e-05],"angular_velocity":[-0.00689,-0.01144,-3e-05]},{"object_id":3,"location":[-0.80341,-1.18685,0.4],"orientation":[0.76059,0.0,0.0,-0.49803],"velocity":[-1e-05,2e-05,-7e-05],"angular_velocity":[0.00245,-0.00362,-0.00016]}]},{"frame_id":46,"trajectory":[{"object_id":0,"location":[-1.50118,0.03756,0.3],"orientation":[-0.00377,0.0,-0.0,0.83665],"velocity":[-3e-05,-2e-05,-6e-05],"angular_velocity":[0.00794,-0.00298,-0.00015]},{"object_id":1,"location":[-0.03206,-0.4592,0.2],"orientation":[0.59292,-0.0,-0.0,0.3373],"velocity":[-2e-05,2e-05,-6e-05],"angular_velocity":[0.00054,-0.01391,0.00017]},{"object_id":2,"location":[-1.27853,-0.68745,0.2],"orientation":[0.30852,-0.0,-0.0,0.63009],"velocity":[-1e-05,6e-05,-5e-05],"angular_velocity":[-0.00689,-0.01144,-3e-05]},{"object_id":3,"location":[-0.80341,-1.18685,0.4],"orientation":[0.76059,0.0,0.0,-0.49803],"velocity":[-1e-05,2e-05,-7e-05],"angular_velocity":[0.00245,-0.00362,-0.00016]}]},{"frame_id":47,"trajectory":[{"object_id":0,"location":[-1.50118,0.03756,0.3],"orientation":[-0.00377,0.0,-0.0,0.83665],"velocity":[-3e-05,-2e-05,-6e-05],"angular_velocity":[0.00794,-0.00298,-0.00015]},{"object_id":1,"location":[-0.03206,-0.4592,0.2],"orientation":[0.59292,-0.0,-0.0,0.3373],"velocity":[-2e-05,3e-05,-6e-05],"angular_velocity":[-0.00022,-0.01448,-0.00025]},{"object_id":2,"location":[-1.27853,-0.68745,0.2],"orientation":[0.30852,-0.0,-0.0,0.63009],"velocity":[-1e-05,6e-05,-5e-05],"angular_velocity":[-0.00689,-0.01144,-3e-05]},{"object_id":3,"location":[-0.80341,-1.18685,0.4],"orientation":[0.76059,0.0,0.0,-0.49803],"velocity":[-1e-05,2e-05,-7e-05],"angular_velocity":[0.00245,-0.00362,-0.00016]}]},{"frame_id":48,"trajectory":[{"object_id":0,"location":[-1.50118,0.03756,0.3],"orientation":[-0.00377,0.0,-0.0,0.83665],"velocity":[-3e-05,-2e-05,-6e-05],"angular_velocity":[0.00794,-0.00298,-0.00015]},{"object_id":1,"location":[-0.03206,-0.4592,0.2],"orientation":[0.59292,-0.0,-0.0,0.3373],"velocity":[-2e-05,2e-05,-5e-05],"angular_velocity":[0.00048,-0.01368,8e-05]},{"object_id":2,"location":[-1.27853,-0.68745,0.2],"orientation":[0.30852,-0.0,-0.0,0.63009],"velocity":[-1e-05,6e-05,-5e-05],"angular_velocity":[-0.00689,-0.01144,-3e-05]},{"object_id":3,"location":[-0.80341,-1.18685,0.4],"orientation":[0.76059,0.0,0.0,-0.49803],"velocity":[-1e-05,2e-05,-7e-05],"angular_velocity":[0.00245,-0.00362,-0.00016]}]},{"frame_id":49,"trajectory":[{"object_id":0,"location":[-1.50118,0.03756,0.3],"orientation":[-0.00377,0.0,-0.0,0.83665],"velocity":[-3e-05,-2e-05,-6e-05],"angular_velocity":[0.00794,-0.00298,-0.00015]},{"object_id":1,"location":[-0.03206,-0.4592,0.2],"orientation":[0.59292,-0.0,-0.0,0.3373],"velocity":[-0.00011,-0.00015,-2e-05],"angular_velocity":[0.02511,-0.02225,0.00028]},{"object_id":2,"location":[-1.27853,-0.68745,0.2],"orientation":[0.30852,-0.0,-0.0,0.63009],"velocity":[-1e-05,6e-05,-5e-05],"angular_velocity":[-0.00689,-0.01144,-3e-05]},{"object_id":3,"location":[-0.80341,-1.18685,0.4],"orientation":[0.76059,0.0,0.0,-0.49803],"velocity":[-1e-05,2e-05,-7e-05],"angular_velocity":[0.00245,-0.00362,-0.00016]}]},{"frame_id":50,"trajectory":[{"object_id":0,"location":[-1.50118,0.03756,0.3],"orientation":[-0.00377,0.0,-0.0,0.83665],"velocity":[-3e-05,-2e-05,-6e-05],"angular_velocity":[0.00794,-0.00298,-0.00015]},{"object_id":1,"location":[-0.03206,-0.4592,0.2],"orientation":[0.59292,-0.0,-0.0,0.3373],"velocity":[-3e-05,2e-05,-6e-05],"angular_velocity":[0.00068,-0.01696,0.0001]},{"object_id":2,"location":[-1.27853,-0.68745,0.2],"orientation":[0.30852,-0.0,-0.0,0.63009],"velocity":[-1e-05,6e-05,-5e-05],"angular_velocity":[-0.00689,-0.01144,-3e-05]},{"object_id":3,"location":[-0.80341,-1.18685,0.4],"orientation":[0.76059,0.0,0.0,-0.49803],"velocity":[-1e-05,2e-05,-7e-05],"angular_velocity":[0.00245,-0.00362,-0.00016]}]},{"frame_id":51,"trajectory":[{"object_id":0,"location":[-1.50118,0.03756,0.3],"orientation":[-0.00377,0.0,-0.0,0.83665],"velocity":[-3e-05,-2e-05,-6e-05],"angular_velocity":[0.00794,-0.00298,-0.00015]},{"object_id":1,"location":[-0.03206,-0.4592,0.2],"orientation":[0.59292,-0.0,-0.0,0.3373],"velocity":[-3e-05,2e-05,-6e-05],"angular_velocity":[0.00068,-0.01696,0.0001]},{"object_id":2,"location":[-1.27853,-0.68745,0.2],"orientation":[0.30852,-0.0,-0.0,0.63009],"velocity":[-1e-05,6e-05,-5e-05],"angular_velocity":[-0.00689,-0.01144,-3e-05]},{"object_id":3,"location":[-0.80341,-1.18685,0.4],"orientation":[0.76059,0.0,0.0,-0.49803],"velocity":[-1e-05,2e-05,-7e-05],"angular_velocity":[0.00245,-0.00362,-0.00016]}]},{"frame_id":52,"trajectory":[{"object_id":0,"location":[-1.50118,0.03756,0.3],"orientation":[-0.00377,0.0,-0.0,0.83665],"velocity":[-3e-05,-2e-05,-6e-05],"angular_velocity":[0.00794,-0.00298,-0.00015]},{"object_id":1,"location":[-0.03206,-0.4592,0.2],"orientation":[0.59292,-0.0,-0.0,0.3373],"velocity":[-3e-05,2e-05,-6e-05],"angular_velocity":[0.00068,-0.01696,0.0001]},{"object_id":2,"location":[-1.27853,-0.68745,0.2],"orientation":[0.30852,-0.0,-0.0,0.63009],"velocity":[-1e-05,6e-05,-5e-05],"angular_velocity":[-0.00689,-0.01144,-3e-05]},{"object_id":3,"location":[-0.80341,-1.18685,0.4],"orientation":[0.76059,0.0,0.0,-0.49803],"velocity":[-1e-05,2e-05,-7e-05],"angular_velocity":[0.00245,-0.00362,-0.00016]}]},{"frame_id":53,"trajectory":[{"object_id":0,"location":[-1.50118,0.03756,0.3],"orientation":[-0.00377,0.0,-0.0,0.83665],"velocity":[-3e-05,-2e-05,-6e-05],"angular_velocity":[0.00794,-0.00298,-0.00015]},{"object_id":1,"location":[-0.03206,-0.4592,0.2],"orientation":[0.59292,-0.0,-0.0,0.3373],"velocity":[-3e-05,2e-05,-6e-05],"angular_velocity":[0.00068,-0.01696,0.0001]},{"object_id":2,"location":[-1.27853,-0.68745,0.2],"orientation":[0.30852,-0.0,-0.0,0.63009],"velocity":[-1e-05,6e-05,-5e-05],"angular_velocity":[-0.00689,-0.01144,-3e-05]},{"object_id":3,"location":[-0.80341,-1.18685,0.4],"orientation":[0.76059,0.0,0.0,-0.49803],"velocity":[-1e-05,2e-05,-7e-05],"angular_velocity":[0.00245,-0.00362,-0.00016]}]},{"frame_id":54,"trajectory":[{"object_id":0,"location":[-1.50118,0.03756,0.3],"orientation":[-0.00377,0.0,-0.0,0.83665],"velocity":[-3e-05,-2e-05,-6e-05],"angular_velocity":[0.00794,-0.00298,-0.00015]},{"object_id":1,"location":[-0.03206,-0.4592,0.2],"orientation":[0.59292,-0.0,-0.0,0.3373],"velocity":[-3e-05,2e-05,-6e-05],"angular_velocity":[0.00068,-0.01696,0.0001]},{"object_id":2,"location":[-1.27853,-0.68745,0.2],"orientation":[0.30852,-0.0,-0.0,0.63009],"velocity":[-1e-05,6e-05,-5e-05],"angular_velocity":[-0.00689,-0.01144,-3e-05]},{"object_id":3,"location":[-0.80341,-1.18685,0.4],"orientation":[0.76059,0.0,0.0,-0.49803],"velocity":[-1e-05,2e-05,-7e-05],"angular_velocity":[0.00245,-0.00362,-0.00016]}]},{"frame_id":55,"trajectory":[{"object_id":0,"location":[-1.50118,0.03756,0.3],"orientation":[-0.00377,0.0,-0.0,0.83665],"velocity":[-3e-05,-2e-05,-6e-05],"angular_velocity":[0.00794,-0.00298,-0.00015]},{"object_id":1,"location":[-0.03206,-0.4592,0.2],"orientation":[0.59292,-0.0,-0.0,0.3373],"velocity":[-3e-05,2e-05,-6e-05],"angular_velocity":[0.00068,-0.01696,0.0001]},{"object_id":2,"location":[-1.27853,-0.68745,0.2],"orientation":[0.30852,-0.0,-0.0,0.63009],"velocity":[-1e-05,6e-05,-5e-05],"angular_velocity":[-0.00689,-0.01144,-3e-05]},{"object_id":3,"location":[-0.80341,-1.18685,0.4],"orientation":[0.76059,0.0,0.0,-0.49803],"velocity":[-1e-05,2e-05,-7e-05],"angular_velocity":[0.00245,-0.00362,-0.00016]}]},{"frame_id":56,"trajectory":[{"object_id":0,"location":[-1.50118,0.03756,0.3],"orientation":[-0.00377,0.0,-0.0,0.83665],"velocity":[-3e-05,-2e-05,-6e-05],"angular_velocity":[0.00794,-0.00298,-0.00015]},{"object_id":1,"location":[-0.03206,-0.4592,0.2],"orientation":[0.59292,-0.0,-0.0,0.3373],"velocity":[-3e-05,2e-05,-6e-05],"angular_velocity":[0.00068,-0.01696,0.0001]},{"object_id":2,"location":[-1.27853,-0.68745,0.2],"orientation":[0.30852,-0.0,-0.0,0.63009],"velocity":[-1e-05,6e-05,-5e-05],"angular_velocity":[-0.00689,-0.01144,-3e-05]},{"object_id":3,"location":[-0.80341,-1.18685,0.4],"orientation":[0.76059,0.0,0.0,-0.49803],"velocity":[-1e-05,2e-05,-7e-05],"angular_velocity":[0.00245,-0.00362,-0.00016]}]},{"frame_id":57,"trajectory":[{"object_id":0,"location":[-1.50118,0.03756,0.3],"orientation":[-0.00377,0.0,-0.0,0.83665],"velocity":[-3e-05,-2e-05,-6e-05],"angular_velocity":[0.00794,-0.00298,-0.00015]},{"object_id":1,"location":[-0.03206,-0.4592,0.2],"orientation":[0.59292,-0.0,-0.0,0.3373],"velocity":[-3e-05,2e-05,-6e-05],"angular_velocity":[0.00068,-0.01696,0.0001]},{"object_id":2,"location":[-1.27853,-0.68745,0.2],"orientation":[0.30852,-0.0,-0.0,0.63009],"velocity":[-1e-05,6e-05,-5e-05],"angular_velocity":[-0.00689,-0.01144,-3e-05]},{"object_id":3,"location":[-0.80341,-1.18685,0.4],"orientation":[0.76059,0.0,0.0,-0.49803],"velocity":[-1e-05,2e-05,-7e-05],"angular_velocity":[0.00245,-0.00362,-0.00016]}]},{"frame_id":58,"trajectory":[{"object_id":0,"location":[-1.50118,0.03756,0.3],"orientation":[-0.00377,0.0,-0.0,0.83665],"velocity":[-3e-05,-2e-05,-6e-05],"angular_velocity":[0.00794,-0.00298,-0.00015]},{"object_id":1,"location":[-0.03206,-0.4592,0.2],"orientation":[0.59292,-0.0,-0.0,0.3373],"velocity":[-3e-05,2e-05,-6e-05],"angular_velocity":[0.00068,-0.01696,0.0001]},{"object_id":2,"location":[-1.27853,-0.68745,0.2],"orientation":[0.30852,-0.0,-0.0,0.63009],"velocity":[-1e-05,6e-05,-5e-05],"angular_velocity":[-0.00689,-0.01144,-3e-05]},{"object_id":3,"location":[-0.80341,-1.18685,0.4],"orientation":[0.76059,0.0,0.0,-0.49803],"velocity":[-1e-05,2e-05,-7e-05],"angular_velocity":[0.00245,-0.00362,-0.00016]}]},{"frame_id":59,"trajectory":[{"object_id":0,"location":[-1.50118,0.03756,0.3],"orientation":[-0.00377,0.0,-0.0,0.83665],"velocity":[-3e-05,-2e-05,-6e-05],"angular_velocity":[0.00794,-0.00298,-0.00015]},{"object_id":1,"location":[-0.03206,-0.4592,0.2],"orientation":[0.59292,-0.0,-0.0,0.3373],"velocity":[-3e-05,2e-05,-6e-05],"angular_velocity":[0.00068,-0.01696,0.0001]},{"object_id":2,"location":[-1.27853,-0.68745,0.2],"orientation":[0.30852,-0.0,-0.0,0.63009],"velocity":[-1e-05,6e-05,-5e-05],"angular_velocity":[-0.00689,-0.01144,-3e-05]},{"object_id":3,"location":[-0.80341,-1.18685,0.4],"orientation":[0.76059,0.0,0.0,-0.49803],"velocity":[-1e-05,2e-05,-7e-05],"angular_velocity":[0.00245,-0.00362,-0.00016]}]},{"frame_id":60,"trajectory":[{"object_id":0,"location":[-1.50118,0.03756,0.3],"orientation":[-0.00377,0.0,-0.0,0.83665],"velocity":[-3e-05,-2e-05,-6e-05],"angular_velocity":[0.00794,-0.00298,-0.00015]},{"object_id":1,"location":[-0.03206,-0.4592,0.2],"orientation":[0.59292,-0.0,-0.0,0.3373],"velocity":[-3e-05,2e-05,-6e-05],"angular_velocity":[0.00068,-0.01696,0.0001]},{"object_id":2,"location":[-1.27853,-0.68745,0.2],"orientation":[0.30852,-0.0,-0.0,0.63009],"velocity":[-1e-05,6e-05,-5e-05],"angular_velocity":[-0.00689,-0.01144,-3e-05]},{"object_id":3,"location":[-0.80341,-1.18685,0.4],"orientation":[0.76059,0.0,0.0,-0.49803],"velocity":[-1e-05,2e-05,-7e-05],"angular_velocity":[0.00245,-0.00362,-0.00016]}]},{"frame_id":61,"trajectory":[{"object_id":0,"location":[-1.50118,0.03756,0.3],"orientation":[-0.00377,0.0,-0.0,0.83665],"velocity":[-3e-05,-2e-05,-6e-05],"angular_velocity":[0.00794,-0.00298,-0.00015]},{"object_id":1,"location":[-0.03206,-0.4592,0.2],"orientation":[0.59292,-0.0,-0.0,0.3373],"velocity":[-3e-05,2e-05,-6e-05],"angular_velocity":[0.00068,-0.01696,0.0001]},{"object_id":2,"location":[-1.27853,-0.68745,0.2],"orientation":[0.30852,-0.0,-0.0,0.63009],"velocity":[-1e-05,6e-05,-5e-05],"angular_velocity":[-0.00689,-0.01144,-3e-05]},{"object_id":3,"location":[-0.80341,-1.18685,0.4],"orientation":[0.76059,0.0,0.0,-0.49803],"velocity":[-1e-05,2e-05,-7e-05],"angular_velocity":[0.00245,-0.00362,-0.00016]}]},{"frame_id":62,"trajectory":[{"object_id":0,"location":[-1.50118,0.03756,0.3],"orientation":[-0.00377,0.0,-0.0,0.83665],"velocity":[-3e-05,-2e-05,-6e-05],"angular_velocity":[0.00794,-0.00298,-0.00015]},{"object_id":1,"location":[-0.03206,-0.4592,0.2],"orientation":[0.59292,-0.0,-0.0,0.3373],"velocity":[-3e-05,2e-05,-6e-05],"angular_velocity":[0.00068,-0.01696,0.0001]},{"object_id":2,"location":[-1.27853,-0.68745,0.2],"orientation":[0.30852,-0.0,-0.0,0.63009],"velocity":[-1e-05,6e-05,-5e-05],"angular_velocity":[-0.00689,-0.01144,-3e-05]},{"object_id":3,"location":[-0.80341,-1.18685,0.4],"orientation":[0.76059,0.0,0.0,-0.49803],"velocity":[-1e-05,2e-05,-7e-05],"angular_velocity":[0.00245,-0.00362,-0.00016]}]},{"frame_id":63,"trajectory":[{"object_id":0,"location":[-1.50118,0.03756,0.3],"orientation":[-0.00377,0.0,-0.0,0.83665],"velocity":[-3e-05,-2e-05,-6e-05],"angular_velocity":[0.00794,-0.00298,-0.00015]},{"object_id":1,"location":[-0.03206,-0.4592,0.2],"orientation":[0.59292,-0.0,-0.0,0.3373],"velocity":[-3e-05,2e-05,-6e-05],"angular_velocity":[0.00068,-0.01696,0.0001]},{"object_id":2,"location":[-1.27853,-0.68745,0.2],"orientation":[0.30852,-0.0,-0.0,0.63009],"velocity":[-1e-05,6e-05,-5e-05],"angular_velocity":[-0.00689,-0.01144,-3e-05]},{"object_id":3,"location":[-0.80341,-1.18685,0.4],"orientation":[0.76059,0.0,0.0,-0.49803],"velocity":[-1e-05,2e-05,-7e-05],"angular_velocity":[0.00245,-0.00362,-0.00016]}]},{"frame_id":64,"trajectory":[{"object_id":0,"location":[-1.50118,0.03756,0.3],"orientation":[-0.00377,0.0,-0.0,0.83665],"velocity":[-3e-05,-2e-05,-6e-05],"angular_velocity":[0.00794,-0.00298,-0.00015]},{"object_id":1,"location":[-0.03206,-0.4592,0.2],"orientation":[0.59292,-0.0,-0.0,0.3373],"velocity":[-3e-05,2e-05,-6e-05],"angular_velocity":[0.00068,-0.01696,0.0001]},{"object_id":2,"location":[-1.27853,-0.68745,0.2],"orientation":[0.30852,-0.0,-0.0,0.63009],"velocity":[-1e-05,6e-05,-5e-05],"angular_velocity":[-0.00689,-0.01144,-3e-05]},{"object_id":3,"location":[-0.80341,-1.18685,0.4],"orientation":[0.76059,0.0,0.0,-0.49803],"velocity":[-1e-05,2e-05,-7e-05],"angular_velocity":[0.00245,-0.00362,-0.00016]}]},{"frame_id":65,"trajectory":[{"object_id":0,"location":[-1.50118,0.03756,0.3],"orientation":[-0.00377,0.0,-0.0,0.83665],"velocity":[-3e-05,-2e-05,-6e-05],"angular_velocity":[0.00794,-0.00298,-0.00015]},{"object_id":1,"location":[-0.03206,-0.4592,0.2],"orientation":[0.59292,-0.0,-0.0,0.3373],"velocity":[-3e-05,2e-05,-6e-05],"angular_velocity":[0.00068,-0.01696,0.0001]},{"object_id":2,"location":[-1.27853,-0.68745,0.2],"orientation":[0.30852,-0.0,-0.0,0.63009],"velocity":[-1e-05,6e-05,-5e-05],"angular_velocity":[-0.00689,-0.01144,-3e-05]},{"object_id":3,"location":[-0.80341,-1.18685,0.4],"orientation":[0.76059,0.0,0.0,-0.49803],"velocity":[-1e-05,2e-05,-7e-05],"angular_velocity":[0.00245,-0.00362,-0.00016]}]},{"frame_id":66,"trajectory":[{"object_id":0,"location":[-1.50118,0.03756,0.3],"orientation":[-0.00377,0.0,-0.0,0.83665],"velocity":[-3e-05,-2e-05,-6e-05],"angular_velocity":[0.00794,-0.00298,-0.00015]},{"object_id":1,"location":[-0.03206,-0.4592,0.2],"orientation":[0.59292,-0.0,-0.0,0.3373],"velocity":[-3e-05,2e-05,-6e-05],"angular_velocity":[0.00068,-0.01696,0.0001]},{"object_id":2,"location":[-1.27853,-0.68745,0.2],"orientation":[0.30852,-0.0,-0.0,0.63009],"velocity":[-1e-05,6e-05,-5e-05],"angular_velocity":[-0.00689,-0.01144,-3e-05]},{"object_id":3,"location":[-0.80341,-1.18685,0.4],"orientation":[0.76059,0.0,0.0,-0.49803],"velocity":[-1e-05,2e-05,-7e-05],"angular_velocity":[0.00245,-0.00362,-0.00016]}]},{"frame_id":67,"trajectory":[{"object_id":0,"location":[-1.50118,0.03756,0.3],"orientation":[-0.00377,0.0,-0.0,0.83665],"velocity":[-3e-05,-2e-05,-6e-05],"angular_velocity":[0.00794,-0.00298,-0.00015]},{"object_id":1,"location":[-0.03206,-0.4592,0.2],"orientation":[0.59292,-0.0,-0.0,0.3373],"velocity":[-3e-05,2e-05,-6e-05],"angular_velocity":[0.00068,-0.01696,0.0001]},{"object_id":2,"location":[-1.27853,-0.68745,0.2],"orientation":[0.30852,-0.0,-0.0,0.63009],"velocity":[-1e-05,6e-05,-5e-05],"angular_velocity":[-0.00689,-0.01144,-3e-05]},{"object_id":3,"location":[-0.80341,-1.18685,0.4],"orientation":[0.76059,0.0,0.0,-0.49803],"velocity":[-1e-05,2e-05,-7e-05],"angular_velocity":[0.00245,-0.00362,-0.00016]}]},{"frame_id":68,"trajectory":[{"object_id":0,"location":[-1.50118,0.03756,0.3],"orientation":[-0.00377,0.0,-0.0,0.83665],"velocity":[-3e-05,-2e-05,-6e-05],"angular_velocity":[0.00794,-0.00298,-0.00015]},{"object_id":1,"location":[-0.03206,-0.4592,0.2],"orientation":[0.59292,-0.0,-0.0,0.3373],"velocity":[-3e-05,2e-05,-6e-05],"angular_velocity":[0.00068,-0.01696,0.0001]},{"object_id":2,"location":[-1.27853,-0.68745,0.2],"orientation":[0.30852,-0.0,-0.0,0.63009],"velocity":[-1e-05,6e-05,-5e-05],"angular_velocity":[-0.00689,-0.01144,-3e-05]},{"object_id":3,"location":[-0.80341,-1.18685,0.4],"orientation":[0.76059,0.0,0.0,-0.49803],"velocity":[-1e-05,2e-05,-7e-05],"angular_velocity":[0.00245,-0.00362,-0.00016]}]},{"frame_id":69,"trajectory":[{"object_id":0,"location":[-1.50118,0.03756,0.3],"orientation":[-0.00377,0.0,-0.0,0.83665],"velocity":[-3e-05,-2e-05,-6e-05],"angular_velocity":[0.00794,-0.00298,-0.00015]},{"object_id":1,"location":[-0.03206,-0.4592,0.2],"orientation":[0.59292,-0.0,-0.0,0.3373],"velocity":[-3e-05,2e-05,-6e-05],"angular_velocity":[0.00068,-0.01696,0.0001]},{"object_id":2,"location":[-1.27853,-0.68745,0.2],"orientation":[0.30852,-0.0,-0.0,0.63009],"velocity":[-1e-05,6e-05,-5e-05],"angular_velocity":[-0.00689,-0.01144,-3e-05]},{"object_id":3,"location":[-0.80341,-1.18685,0.4],"orientation":[0.76059,0.0,0.0,-0.49803],"velocity":[-1e-05,2e-05,-7e-05],"angular_velocity":[0.00245,-0.00362,-0.00016]}]},{"frame_id":70,"trajectory":[{"object_id":0,"location":[-1.50118,0.03756,0.3],"orientation":[-0.00377,0.0,-0.0,0.83665],"velocity":[-3e-05,-2e-05,-6e-05],"angular_velocity":[0.00794,-0.00298,-0.00015]},{"object_id":1,"location":[-0.03206,-0.4592,0.2],"orientation":[0.59292,-0.0,-0.0,0.3373],"velocity":[-3e-05,2e-05,-6e-05],"angular_velocity":[0.00068,-0.01696,0.0001]},{"object_id":2,"location":[-1.27853,-0.68745,0.2],"orientation":[0.30852,-0.0,-0.0,0.63009],"velocity":[-1e-05,6e-05,-5e-05],"angular_velocity":[-0.00689,-0.01144,-3e-05]},{"object_id":3,"location":[-0.80341,-1.18685,0.4],"orientation":[0.76059,0.0,0.0,-0.49803],"velocity":[-1e-05,2e-05,-7e-05],"angular_velocity":[0.00245,-0.00362,-0.00016]}]},{"frame_id":71,"trajectory":[{"object_id":0,"location":[-1.50118,0.03756,0.3],"orientation":[-0.00377,0.0,-0.0,0.83665],"velocity":[-3e-05,-2e-05,-6e-05],"angular_velocity":[0.00794,-0.00298,-0.00015]},{"object_id":1,"location":[-0.03206,-0.4592,0.2],"orientation":[0.59292,-0.0,-0.0,0.3373],"velocity":[-3e-05,2e-05,-6e-05],"angular_velocity":[0.00068,-0.01696,0.0001]},{"object_id":2,"location":[-1.27853,-0.68745,0.2],"orientation":[0.30852,-0.0,-0.0,0.63009],"velocity":[-1e-05,6e-05,-5e-05],"angular_velocity":[-0.00689,-0.01144,-3e-05]},{"object_id":3,"location":[-0.80341,-1.18685,0.4],"orientation":[0.76059,0.0,0.0,-0.49803],"velocity":[-1e-05,2e-05,-7e-05],"angular_velocity":[0.00245,-0.00362,-0.00016]}]},{"frame_id":72,"trajectory":[{"object_id":0,"location":[-1.50118,0.03756,0.3],"orientation":[-0.00377,0.0,-0.0,0.83665],"velocity":[-3e-05,-2e-05,-6e-05],"angular_velocity":[0.00794,-0.00298,-0.00015]},{"object_id":1,"location":[-0.03206,-0.4592,0.2],"orientation":[0.59292,-0.0,-0.0,0.3373],"velocity":[-3e-05,2e-05,-6e-05],"angular_velocity":[0.00068,-0.01696,0.0001]},{"object_id":2,"location":[-1.27853,-0.68745,0.2],"orientation":[0.30852,-0.0,-0.0,0.63009],"velocity":[-1e-05,6e-05,-5e-05],"angular_velocity":[-0.00689,-0.01144,-3e-05]},{"object_id":3,"location":[-0.80341,-1.18685,0.4],"orientation":[0.76059,0.0,0.0,-0.49803],"velocity":[-1e-05,2e-05,-7e-05],"angular_velocity":[0.00245,-0.00362,-0.00016]}]},{"frame_id":73,"trajectory":[{"object_id":0,"location":[-1.50118,0.03756,0.3],"orientation":[-0.00377,0.0,-0.0,0.83665],"velocity":[-3e-05,-2e-05,-6e-05],"angular_velocity":[0.00794,-0.00298,-0.00015]},{"object_id":1,"location":[-0.03206,-0.4592,0.2],"orientation":[0.59292,-0.0,-0.0,0.3373],"velocity":[-3e-05,2e-05,-6e-05],"angular_velocity":[0.00068,-0.01696,0.0001]},{"object_id":2,"location":[-1.27853,-0.68745,0.2],"orientation":[0.30852,-0.0,-0.0,0.63009],"velocity":[-1e-05,6e-05,-5e-05],"angular_velocity":[-0.00689,-0.01144,-3e-05]},{"object_id":3,"location":[-0.80341,-1.18685,0.4],"orientation":[0.76059,0.0,0.0,-0.49803],"velocity":[-1e-05,2e-05,-7e-05],"angular_velocity":[0.00245,-0.00362,-0.00016]}]},{"frame_id":74,"trajectory":[{"object_id":0,"location":[-1.50118,0.03756,0.3],"orientation":[-0.00377,0.0,-0.0,0.83665],"velocity":[-3e-05,-2e-05,-6e-05],"angular_velocity":[0.00794,-0.00298,-0.00015]},{"object_id":1,"location":[-0.03206,-0.4592,0.2],"orientation":[0.59292,-0.0,-0.0,0.3373],"velocity":[-3e-05,2e-05,-6e-05],"angular_velocity":[0.00068,-0.01696,0.0001]},{"object_id":2,"location":[-1.27853,-0.68745,0.2],"orientation":[0.30852,-0.0,-0.0,0.63009],"velocity":[-1e-05,6e-05,-5e-05],"angular_velocity":[-0.00689,-0.01144,-3e-05]},{"object_id":3,"location":[-0.80341,-1.18685,0.4],"orientation":[0.76059,0.0,0.0,-0.49803],"velocity":[-1e-05,2e-05,-7e-05],"angular_velocity":[0.00245,-0.00362,-0.00016]}]},{"frame_id":75,"trajectory":[{"object_id":0,"location":[-1.50118,0.03756,0.3],"orientation":[-0.00377,0.0,-0.0,0.83665],"velocity":[-3e-05,-2e-05,-6e-05],"angular_velocity":[0.00794,-0.00298,-0.00015]},{"object_id":1,"location":[-0.03206,-0.4592,0.2],"orientation":[0.59292,-0.0,-0.0,0.3373],"velocity":[-3e-05,2e-05,-6e-05],"angular_velocity":[0.00068,-0.01696,0.0001]},{"object_id":2,"location":[-1.27853,-0.68745,0.2],"orientation":[0.30852,-0.0,-0.0,0.63009],"velocity":[-1e-05,6e-05,-5e-05],"angular_velocity":[-0.00689,-0.01144,-3e-05]},{"object_id":3,"location":[-0.80341,-1.18685,0.4],"orientation":[0.76059,0.0,0.0,-0.49803],"velocity":[-1e-05,2e-05,-7e-05],"angular_velocity":[0.00245,-0.00362,-0.00016]}]},{"frame_id":76,"trajectory":[{"object_id":0,"location":[-1.50118,0.03756,0.3],"orientation":[-0.00377,0.0,-0.0,0.83665],"velocity":[-3e-05,-2e-05,-6e-05],"angular_velocity":[0.00794,-0.00298,-0.00015]},{"object_id":1,"location":[-0.03206,-0.4592,0.2],"orientation":[0.59292,-0.0,-0.0,0.3373],"velocity":[-3e-05,2e-05,-6e-05],"angular_velocity":[0.00068,-0.01696,0.0001]},{"object_id":2,"location":[-1.27853,-0.68745,0.2],"orientation":[0.30852,-0.0,-0.0,0.63009],"velocity":[-1e-05,6e-05,-5e-05],"angular_velocity":[-0.00689,-0.01144,-3e-05]},{"object_id":3,"location":[-0.80341,-1.18685,0.4],"orientation":[0.76059,0.0,0.0,-0.49803],"velocity":[-1e-05,2e-05,-7e-05],"angular_velocity":[0.00245,-0.00362,-0.00016]}]},{"frame_id":77,"trajectory":[{"object_id":0,"location":[-1.50118,0.03756,0.3],"orientation":[-0.00377,0.0,-0.0,0.83665],"velocity":[-3e-05,-2e-05,-6e-05],"angular_velocity":[0.00794,-0.00298,-0.00015]},{"object_id":1,"location":[-0.03206,-0.4592,0.2],"orientation":[0.59292,-0.0,-0.0,0.3373],"velocity":[-3e-05,2e-05,-6e-05],"angular_velocity":[0.00068,-0.01696,0.0001]},{"object_id":2,"location":[-1.27853,-0.68745,0.2],"orientation":[0.30852,-0.0,-0.0,0.63009],"velocity":[-1e-05,6e-05,-5e-05],"angular_velocity":[-0.00689,-0.01144,-3e-05]},{"object_id":3,"location":[-0.80341,-1.18685,0.4],"orientation":[0.76059,0.0,0.0,-0.49803],"velocity":[-1e-05,2e-05,-7e-05],"angular_velocity":[0.00245,-0.00362,-0.00016]}]},{"frame_id":78,"trajectory":[{"object_id":0,"location":[-1.50118,0.03756,0.3],"orientation":[-0.00377,0.0,-0.0,0.83665],"velocity":[-3e-05,-2e-05,-6e-05],"angular_velocity":[0.00794,-0.00298,-0.00015]},{"object_id":1,"location":[-0.03206,-0.4592,0.2],"orientation":[0.59292,-0.0,-0.0,0.3373],"velocity":[-3e-05,2e-05,-6e-05],"angular_velocity":[0.00068,-0.01696,0.0001]},{"object_id":2,"location":[-1.27853,-0.68745,0.2],"orientation":[0.30852,-0.0,-0.0,0.63009],"velocity":[-1e-05,6e-05,-5e-05],"angular_velocity":[-0.00689,-0.01144,-3e-05]},{"object_id":3,"location":[-0.80341,-1.18685,0.4],"orientation":[0.76059,0.0,0.0,-0.49803],"velocity":[-1e-05,2e-05,-7e-05],"angular_velocity":[0.00245,-0.00362,-0.00016]}]},{"frame_id":79,"trajectory":[{"object_id":0,"location":[-1.50118,0.03756,0.3],"orientation":[-0.00377,0.0,-0.0,0.83665],"velocity":[-3e-05,-2e-05,-6e-05],"angular_velocity":[0.00794,-0.00298,-0.00015]},{"object_id":1,"location":[-0.03206,-0.4592,0.2],"orientation":[0.59292,-0.0,-0.0,0.3373],"velocity":[-3e-05,2e-05,-6e-05],"angular_velocity":[0.00068,-0.01696,0.0001]},{"object_id":2,"location":[-1.27853,-0.68745,0.2],"orientation":[0.30852,-0.0,-0.0,0.63009],"velocity":[-1e-05,6e-05,-5e-05],"angular_velocity":[-0.00689,-0.01144,-3e-05]},{"object_id":3,"location":[-0.80341,-1.18685,0.4],"orientation":[0.76059,0.0,0.0,-0.49803],"velocity":[-1e-05,2e-05,-7e-05],"angular_velocity":[0.00245,-0.00362,-0.00016]}]},{"frame_id":80,"trajectory":[{"object_id":0,"location":[-1.50118,0.03756,0.3],"orientation":[-0.00377,0.0,-0.0,0.83665],"velocity":[-3e-05,-2e-05,-6e-05],"angular_velocity":[0.00794,-0.00298,-0.00015]},{"object_id":1,"location":[-0.03206,-0.4592,0.2],"orientation":[0.59292,-0.0,-0.0,0.3373],"velocity":[-3e-05,2e-05,-6e-05],"angular_velocity":[0.00068,-0.01696,0.0001]},{"object_id":2,"location":[-1.27853,-0.68745,0.2],"orientation":[0.30852,-0.0,-0.0,0.63009],"velocity":[-1e-05,6e-05,-5e-05],"angular_velocity":[-0.00689,-0.01144,-3e-05]},{"object_id":3,"location":[-0.80341,-1.18685,0.4],"orientation":[0.76059,0.0,0.0,-0.49803],"velocity":[-1e-05,2e-05,-7e-05],"angular_velocity":[0.00245,-0.00362,-0.00016]}]},{"frame_id":81,"trajectory":[{"object_id":0,"location":[-1.50118,0.03756,0.3],"orientation":[-0.00377,0.0,-0.0,0.83665],"velocity":[-3e-05,-2e-05,-6e-05],"angular_velocity":[0.00794,-0.00298,-0.00015]},{"object_id":1,"location":[-0.03206,-0.4592,0.2],"orientation":[0.59292,-0.0,-0.0,0.3373],"velocity":[-3e-05,2e-05,-6e-05],"angular_velocity":[0.00068,-0.01696,0.0001]},{"object_id":2,"location":[-1.27853,-0.68745,0.2],"orientation":[0.30852,-0.0,-0.0,0.63009],"velocity":[-1e-05,6e-05,-5e-05],"angular_velocity":[-0.00689,-0.01144,-3e-05]},{"object_id":3,"location":[-0.80341,-1.18685,0.4],"orientation":[0.76059,0.0,0.0,-0.49803],"velocity":[-1e-05,2e-05,-7e-05],"angular_velocity":[0.00245,-0.00362,-0.00016]}]},{"frame_id":82,"trajectory":[{"object_id":0,"location":[-1.50118,0.03756,0.3],"orientation":[-0.00377,0.0,-0.0,0.83665],"velocity":[-3e-05,-2e-05,-6e-05],"angular_velocity":[0.00794,-0.00298,-0.00015]},{"object_id":1,"location":[-0.03206,-0.4592,0.2],"orientation":[0.59292,-0.0,-0.0,0.3373],"velocity":[-3e-05,2e-05,-6e-05],"angular_velocity":[0.00068,-0.01696,0.0001]},{"object_id":2,"location":[-1.27853,-0.68745,0.2],"orientation":[0.30852,-0.0,-0.0,0.63009],"velocity":[-1e-05,6e-05,-5e-05],"angular_velocity":[-0.00689,-0.01144,-3e-05]},{"object_id":3,"location":[-0.80341,-1.18685,0.4],"orientation":[0.76059,0.0,0.0,-0.49803],"velocity":[-1e-05,2e-05,-7e-05],"angular_velocity":[0.00245,-0.00362,-0.00016]}]},{"frame_id":83,"trajectory":[{"object_id":0,"location":[-1.50118,0.03756,0.3],"orientation":[-0.00377,0.0,-0.0,0.83665],"velocity":[-3e-05,-2e-05,-6e-05],"angular_velocity":[0.00794,-0.00298,-0.00015]},{"object_id":1,"location":[-0.03206,-0.4592,0.2],"orientation":[0.59292,-0.0,-0.0,0.3373],"velocity":[-3e-05,2e-05,-6e-05],"angular_velocity":[0.00068,-0.01696,0.0001]},{"object_id":2,"location":[-1.27853,-0.68745,0.2],"orientation":[0.30852,-0.0,-0.0,0.63009],"velocity":[-1e-05,6e-05,-5e-05],"angular_velocity":[-0.00689,-0.01144,-3e-05]},{"object_id":3,"location":[-0.80341,-1.18685,0.4],"orientation":[0.76059,0.0,0.0,-0.49803],"velocity":[-1e-05,2e-05,-7e-05],"angular_velocity":[0.00245,-0.00362,-0.00016]}]},{"frame_id":84,"trajectory":[{"object_id":0,"location":[-1.50118,0.03756,0.3],"orientation":[-0.00377,0.0,-0.0,0.83665],"velocity":[-3e-05,-2e-05,-6e-05],"angular_velocity":[0.00794,-0.00298,-0.00015]},{"object_id":1,"location":[-0.03206,-0.4592,0.2],"orientation":[0.59292,-0.0,-0.0,0.3373],"velocity":[-3e-05,2e-05,-6e-05],"angular_velocity":[0.00068,-0.01696,0.0001]},{"object_id":2,"location":[-1.27853,-0.68745,0.2],"orientation":[0.30852,-0.0,-0.0,0.63009],"velocity":[-1e-05,6e-05,-5e-05],"angular_velocity":[-0.00689,-0.01144,-3e-05]},{"object_id":3,"location":[-0.80341,-1.18685,0.4],"orientation":[0.76059,0.0,0.0,-0.49803],"velocity":[-1e-05,2e-05,-7e-05],"angular_velocity":[0.00245,-0.00362,-0.00016]}]},{"frame_id":85,"trajectory":[{"object_id":0,"location":[-1.50118,0.03756,0.3],"orientation":[-0.00377,0.0,-0.0,0.83665],"velocity":[-3e-05,-2e-05,-6e-05],"angular_velocity":[0.00794,-0.00298,-0.00015]},{"object_id":1,"location":[-0.03206,-0.4592,0.2],"orientation":[0.59292,-0.0,-0.0,0.3373],"velocity":[-3e-05,2e-05,-6e-05],"angular_velocity":[0.00068,-0.01696,0.0001]},{"object_id":2,"location":[-1.27853,-0.68745,0.2],"orientation":[0.30852,-0.0,-0.0,0.63009],"velocity":[-1e-05,6e-05,-5e-05],"angular_velocity":[-0.00689,-0.01144,-3e-05]},{"object_id":3,"location":[-0.80341,-1.18685,0.4],"orientation":[0.76059,0.0,0.0,-0.49803],"velocity":[-1e-05,2e-05,-7e-05],"angular_velocity":[0.00245,-0.00362,-0.00016]}]},{"frame_id":86,"trajectory":[{"object_id":0,"location":[-1.50118,0.03756,0.3],"orientation":[-0.00377,0.0,-0.0,0.83665],"velocity":[-3e-05,-2e-05,-6e-05],"angular_velocity":[0.00794,-0.00298,-0.00015]},{"object_id":1,"location":[-0.03206,-0.4592,0.2],"orientation":[0.59292,-0.0,-0.0,0.3373],"velocity":[-3e-05,2e-05,-6e-05],"angular_velocity":[0.00068,-0.01696,0.0001]},{"object_id":2,"location":[-1.27853,-0.68745,0.2],"orientation":[0.30852,-0.0,-0.0,0.63009],"velocity":[-1e-05,6e-05,-5e-05],"angular_velocity":[-0.00689,-0.01144,-3e-05]},{"object_id":3,"location":[-0.80341,-1.18685,0.4],"orientation":[0.76059,0.0,0.0,-0.49803],"velocity":[-1e-05,2e-05,-7e-05],"angular_velocity":[0.00245,-0.00362,-0.00016]}]},{"frame_id":87,"trajectory":[{"object_id":0,"location":[-1.50118,0.03756,0.3],"orientation":[-0.00377,0.0,-0.0,0.83665],"velocity":[-3e-05,-2e-05,-6e-05],"angular_velocity":[0.00794,-0.00298,-0.00015]},{"object_id":1,"location":[-0.03206,-0.4592,0.2],"orientation":[0.59292,-0.0,-0.0,0.3373],"velocity":[-3e-05,2e-05,-6e-05],"angular_velocity":[0.00068,-0.01696,0.0001]},{"object_id":2,"location":[-1.27853,-0.68745,0.2],"orientation":[0.30852,-0.0,-0.0,0.63009],"velocity":[-1e-05,6e-05,-5e-05],"angular_velocity":[-0.00689,-0.01144,-3e-05]},{"object_id":3,"location":[-0.80341,-1.18685,0.4],"orientation":[0.76059,0.0,0.0,-0.49803],"velocity":[-1e-05,2e-05,-7e-05],"angular_velocity":[0.00245,-0.00362,-0.00016]}]},{"frame_id":88,"trajectory":[{"object_id":0,"location":[-1.50118,0.03756,0.3],"orientation":[-0.00377,0.0,-0.0,0.83665],"velocity":[-3e-05,-2e-05,-6e-05],"angular_velocity":[0.00794,-0.00298,-0.00015]},{"object_id":1,"location":[-0.03206,-0.4592,0.2],"orientation":[0.59292,-0.0,-0.0,0.3373],"velocity":[-3e-05,2e-05,-6e-05],"angular_velocity":[0.00068,-0.01696,0.0001]},{"object_id":2,"location":[-1.27853,-0.68745,0.2],"orientation":[0.30852,-0.0,-0.0,0.63009],"velocity":[-1e-05,6e-05,-5e-05],"angular_velocity":[-0.00689,-0.01144,-3e-05]},{"object_id":3,"location":[-0.80341,-1.18685,0.4],"orientation":[0.76059,0.0,0.0,-0.49803],"velocity":[-1e-05,2e-05,-7e-05],"angular_velocity":[0.00245,-0.00362,-0.00016]}]},{"frame_id":89,"trajectory":[{"object_id":0,"location":[-1.50118,0.03756,0.3],"orientation":[-0.00377,0.0,-0.0,0.83665],"velocity":[-3e-05,-2e-05,-6e-05],"angular_velocity":[0.00794,-0.00298,-0.00015]},{"object_id":1,"location":[-0.03206,-0.4592,0.2],"orientation":[0.59292,-0.0,-0.0,0.3373],"velocity":[-3e-05,2e-05,-6e-05],"angular_velocity":[0.00068,-0.01696,0.0001]},{"object_id":2,"location":[-1.27853,-0.68745,0.2],"orientation":[0.30852,-0.0,-0.0,0.63009],"velocity":[-1e-05,6e-05,-5e-05],"angular_velocity":[-0.00689,-0.01144,-3e-05]},{"object_id":3,"location":[-0.80341,-1.18685,0.4],"orientation":[0.76059,0.0,0.0,-0.49803],"velocity":[-1e-05,2e-05,-7e-05],"angular_velocity":[0.00245,-0.00362,-0.00016]}]}],"collision":[{"object_ids":[0,1],"frame_id":5,"location":[-0.7253164649009705,0.5062631964683533,0.3999999165534973]},{"object_ids":[-1,2],"frame_id":6,"location":[-2.0,-0.09204576909542084,0.40000009536743164]},{"object_ids":[0,1],"frame_id":7,"location":[-0.5811200141906738,0.6700499057769775,0.40504664182662964]},{"object_ids":[1,3],"frame_id":19,"location":[-0.5541782975196838,-0.670072078704834,6.854534149169922e-07]},{"object_ids":[2,3],"frame_id":20,"location":[-1.035415530204773,-0.8422479629516602,1.4901161193847656e-08]}]}