{"object_property":[{"object_id":0,"shape":"cube","size":"medium","material":"marble","density":4,"mass":0.864,"friction":0.25,"restitution":0.6},{"object_id":1,"shape":"cube","size":"large","material":"RedUnknown","density":7.58376,"mass":3.88289,"friction":0.24917,"restitution":0.46265},{"object_id":2,"shape":"cube","size":"small","material":"porcelain","density":4,"mass":0.256,"friction":0.125,"restitution":0.9}],"trajectory":[{"frame_id":0,"trajectory":[{"object_id":0,"location":[-0.65016,0.2369,0.3],"orientation":[0.77519,0.0,0.0,0.28739],"velocity":[2.70595,-2.17431,0.0],"angular_velocity":[0.0,0.0,0.0]},{"object_id":1,"location":[0.85323,-0.04969,0.4],"orientation":[0.58078,0.0,0.0,0.6876],"velocity":[-3.90997,-0.95839,0.0],"angular_velocity":[0.0,0.0,0.0]},{"object_id":2,"location":[-0.23904,0.81996,0.2],"orientation":[0.71467,0.0,0.0,-0.1665],"velocity":[0.98911,1.73829,0.0],"angular_velocity":[0.0,0.0,0.0]}]},{"frame_id":1,"trajectory":[{"object_id":0,"location":[-0.56116,0.16539,0.3],"orientation":[0.77519,-0.0,-0.0,0.28739],"velocity":[2.64223,-2.1231,-0.0],"angular_velocity":[0.0,0.0,0.00061]},{"object_id":1,"location":[0.72438,-0.08127,0.4],"orientation":[0.58078,-0.0,-0.0,0.6876],"velocity":[-3.83083,-0.93899,-1e-05],"angular_velocity":[0.0002,-0.00114,-0.00017]},{"object_id":2,"location":[-0.20644,0.87723,0.2],"orientation":[0.71467,-0.0,0.0,-0.1665],"velocity":[0.9689,1.70276,-0.0],"angular_velocity":[-0.00046,9e-05,-0.00018]}]},{"frame_id":2,"trajectory":[{"object_id":0,"location":[-0.47428,0.09558,0.3],"orientation":[0.77519,0.0,0.0,0.28739],"velocity":[2.57851,-2.0719,-3e-05],"angular_velocity":[0.00922,0.02965,0.0012]},{"object_id":1,"location":[0.59817,-0.11221,0.4],"orientation":[0.58078,0.0,-0.0,0.6876],"velocity":[-3.75169,-0.91959,-0.0],"angular_velocity":[0.00016,8e-05,-0.00018]},{"object_id":2,"location":[-0.17453,0.93333,0.2],"orientation":[0.71467,0.0,0.0,-0.1665],"velocity":[0.94868,1.66724,-0.0],"angular_velocity":[-0.00031,0.00059,-0.0002]}]},{"frame_id":3,"trajectory":[{"object_id":0,"location":[-0.38952,0.02747,0.3],"orientation":[0.77519,0.0,0.0,0.28739],"velocity":[2.51477,-2.02069,-0.0],"angular_velocity":[-0.00021,-0.00027,0.00205]},{"object_id":1,"location":[0.47459,-0.1425,0.4],"orientation":[0.58078,0.0,-0.0,0.6876],"velocity":[-3.67255,-0.90019,-0.0],"angular_velocity":[0.00025,0.00022,-0.00031]},{"object_id":2,"location":[-0.14328,0.98824,0.2],"orientation":[0.71467,0.0,0.0,-0.1665],"velocity":[0.92847,1.63171,-1e-05],"angular_velocity":[-0.00095,0.00178,-0.00022]}]},{"frame_id":4,"trajectory":[{"object_id":0,"location":[-0.47126,-0.02986,0.3],"orientation":[0.75868,0.0,0.0,0.32061],"velocity":[-3.3741,-1.65413,-1e-05],"angular_velocity":[-0.00095,-0.0003,218.15677]},{"object_id":1,"location":[0.39051,-0.17389,0.40039],"orientation":[0.67123,-0.00029,-0.00029,0.59592],"velocity":[-2.29349,-0.94373,-0.04931],"angular_velocity":[-0.11528,7.25015,-118.82854]},{"object_id":2,"location":[-0.11271,1.04196,0.2],"orientation":[0.71467,-0.0,0.0,-0.1665],"velocity":[0.90825,1.59618,-0.0],"angular_velocity":[1e-05,-0.0,-0.00027]}]},{"frame_id":5,"trajectory":[{"object_id":0,"location":[-0.58241,-0.08431,0.3],"orientation":[0.7374,0.0,-0.0,0.35709],"velocity":[-3.30342,-1.61699,-0.0],"angular_velocity":[-9e-05,3e-05,214.53645]},{"object_id":1,"location":[0.31568,-0.2046,0.4],"orientation":[0.69083,-0.0,-0.0,0.57767],"velocity":[-2.21082,-0.90591,-1e-05],"angular_velocity":[0.00087,0.00167,-112.01794]},{"object_id":2,"location":[-0.08282,1.0945,0.2],"orientation":[0.71467,-0.0,-0.0,-0.1665],"velocity":[0.88804,1.56066,-1e-05],"angular_velocity":[-0.00156,0.00162,-0.00042]}]},{"frame_id":6,"trajectory":[{"object_id":0,"location":[-0.69117,-0.13752,0.3],"orientation":[0.71415,0.0,-0.0,0.39082],"velocity":[-3.231,-1.58005,-0.0],"angular_velocity":[-0.00048,-0.00019,213.12747]},{"object_id":1,"location":[0.24334,-0.23419,0.4],"orientation":[0.70882,-0.0,-0.0,0.55945],"velocity":[-2.13838,-0.87364,-1e-05],"angular_velocity":[0.00202,-0.00223,-106.35928]},{"object_id":2,"location":[-0.0536,1.14586,0.2],"orientation":[0.71467,-0.0,-0.0,-0.1665],"velocity":[0.86782,1.52513,-1e-05],"angular_velocity":[-0.00112,0.0009,-0.0006]}]},{"frame_id":7,"trajectory":[{"object_id":0,"location":[-0.79752,-0.18951,0.3],"orientation":[0.68924,0.0,0.0,0.42142],"velocity":[-3.1589,-1.54416,0.0],"angular_velocity":[-0.0,0.0,207.8652]},{"object_id":1,"location":[0.17343,-0.26272,0.4],"orientation":[0.72536,-0.0,-0.0,0.54137],"velocity":[-2.06544,-0.84191,0.0],"angular_velocity":[-0.0047,0.00728,-100.94636]},{"object_id":2,"location":[-0.02505,1.19603,0.2],"orientation":[0.71467,-0.0,-0.0,-0.1665],"velocity":[0.84761,1.48961,-1e-05],"angular_velocity":[-0.00111,0.0009,-0.00071]}]},{"frame_id":8,"trajectory":[{"object_id":0,"location":[-0.90147,-0.2403,0.3],"orientation":[0.66343,0.0,-0.0,0.44813],"velocity":[-3.08731,-1.50819,-0.0],"angular_velocity":[-6e-05,6e-05,200.98637]},{"object_id":1,"location":[0.10596,-0.29019,0.4],"orientation":[0.74053,-0.0,0.0,0.52356],"velocity":[-1.99211,-0.81063,-0.0],"angular_velocity":[1e-05,-3e-05,-95.73672]},{"object_id":2,"location":[0.00283,1.24501,0.2],"orientation":[0.71467,-0.0,0.0,-0.1665],"velocity":[0.82739,1.45408,-0.0],"angular_velocity":[-0.00078,0.00068,-0.00066]}]},{"frame_id":9,"trajectory":[{"object_id":0,"location":[-1.00305,-0.28989,0.3],"orientation":[0.63708,0.0,-0.0,0.47081],"velocity":[-3.01623,-1.47158,-0.0],"angular_velocity":[-7e-05,6e-05,193.94464]},{"object_id":1,"location":[0.04093,-0.31663,0.4],"orientation":[0.75444,-0.0,0.0,0.50611],"velocity":[-1.91847,-0.77975,-0.0],"angular_velocity":[0.00016,0.00028,-90.69217]},{"object_id":2,"location":[0.03003,1.29282,0.2],"orientation":[0.71467,-0.0,0.0,-0.1665],"velocity":[0.80718,1.41855,-1e-05],"angular_velocity":[-0.00104,0.00126,-0.00068]}]},{"frame_id":10,"trajectory":[{"object_id":0,"location":[-1.10226,-0.33825,0.3],"orientation":[0.45709,0.0,-0.0,0.65362],"velocity":[-2.94575,-1.43434,-0.0],"angular_velocity":[-7e-05,6e-05,186.66708]},{"object_id":1,"location":[-0.02163,-0.34205,0.4],"orientation":[0.76716,-0.0,0.0,0.48913],"velocity":[-1.84458,-0.7492,-0.0],"angular_velocity":[8e-05,0.0002,-85.7818]},{"object_id":2,"location":[0.05655,1.33944,0.2],"orientation":[0.71467,-0.0,0.0,-0.1665],"velocity":[0.78696,1.38303,-0.0],"angular_velocity":[-0.00039,0.0006,-0.00083]}]},{"frame_id":11,"trajectory":[{"object_id":0,"location":[-1.19914,-0.38535,0.3],"orientation":[0.43438,-0.0,-0.0,0.67729],"velocity":[-2.87597,-1.39652,0.0],"angular_velocity":[-5e-05,8e-05,179.1555]},{"object_id":1,"location":[-0.08173,-0.36646,0.4],"orientation":[0.77878,-0.0,-0.0,0.47268],"velocity":[-1.7705,-0.71894,-1e-05],"angular_velocity":[0.00014,0.00108,-80.97897]},{"object_id":2,"location":[0.08241,1.38487,0.2],"orientation":[0.71467,-0.0,0.0,-0.1665],"velocity":[0.76675,1.3475,-1e-05],"angular_velocity":[-0.00065,0.00118,-0.00092]}]},{"frame_id":12,"trajectory":[{"object_id":0,"location":[-1.29371,-0.43119,0.3],"orientation":[0.41032,0.0,0.0,0.69877],"velocity":[-2.80689,-1.35816,-1e-05],"angular_velocity":[-0.00035,-0.00055,171.48767]},{"object_id":1,"location":[-0.13934,-0.38984,0.4],"orientation":[0.78961,0.0,0.0,0.45646],"velocity":[-1.69585,-0.68823,-2e-05],"angular_velocity":[0.00112,0.00466,-78.49006]},{"object_id":2,"location":[0.10759,1.42912,0.2],"orientation":[0.71467,-0.0,0.0,-0.1665],"velocity":[0.74653,1.31198,-0.0],"angular_velocity":[-0.00052,0.00063,-0.00113]}]},{"frame_id":13,"trajectory":[{"object_id":0,"location":[-1.38599,-0.47573,0.3],"orientation":[0.38544,0.0,-0.0,0.71812],"velocity":[-2.73849,-1.31934,-0.0],"angular_velocity":[-9e-05,4e-05,163.80667]},{"object_id":1,"location":[-0.19448,-0.4122,0.4],"orientation":[0.79963,0.0,0.0,0.4406],"velocity":[-1.62153,-0.65779,-1e-05],"angular_velocity":[0.00049,0.00285,-74.79667]},{"object_id":2,"location":[0.13209,1.47219,0.2],"orientation":[0.71467,-0.0,0.0,-0.1665],"velocity":[0.72632,1.27645,-0.0],"angular_velocity":[-0.00042,0.00072,-0.00116]}]},{"frame_id":14,"trajectory":[{"object_id":0,"location":[-1.476,-0.51898,0.3],"orientation":[0.36017,0.0,-0.0,0.73543],"velocity":[-2.67064,-1.28017,-0.0],"angular_velocity":[-9e-05,4e-05,156.29985]},{"object_id":1,"location":[-0.24715,-0.43351,0.4],"orientation":[0.8089,-0.0,-0.0,0.42513],"velocity":[-1.54769,-0.62584,-0.0],"angular_velocity":[0.0001,0.00049,-71.62645]},{"object_id":2,"location":[0.15592,1.51407,0.2],"orientation":[0.71467,-0.0,0.0,-0.1665],"velocity":[0.7061,1.24092,-0.0],"angular_velocity":[1e-05,-0.0,-0.00123]}]},{"frame_id":15,"trajectory":[{"object_id":0,"location":[-1.56376,-0.56091,0.3],"orientation":[0.33481,0.0,-0.0,0.75082],"velocity":[-2.60315,-1.24074,0.0],"angular_velocity":[-0.00014,6e-05,149.17412]},{"object_id":1,"location":[-0.29736,-0.45376,0.4],"orientation":[0.81734,-0.0,0.0,0.4103],"velocity":[-1.47437,-0.59348,-1e-05],"angular_velocity":[0.00063,0.00323,-68.15673]},{"object_id":2,"location":[0.17908,1.55477,0.2],"orientation":[0.71467,-0.0,0.0,-0.1665],"velocity":[0.68589,1.2054,-0.0],"angular_velocity":[-0.00071,0.00014,-0.00144]}]},{"frame_id":16,"trajectory":[{"object_id":0,"location":[-1.54596,-0.59021,0.3],"orientation":[0.35402,-0.0,-0.0,0.73933],"velocity":[1.31187,-0.80547,-1e-05],"angular_velocity":[0.00094,-0.0009,-153.97858]},{"object_id":1,"location":[-0.34514,-0.47294,0.4],"orientation":[0.82512,-0.0,0.0,0.39593],"velocity":[-1.40139,-0.56123,-1e-05],"angular_velocity":[0.00033,0.00079,-64.97094]},{"object_id":2,"location":[0.20157,1.59428,0.2],"orientation":[0.71467,-0.0,0.0,-0.1665],"velocity":[0.66567,1.16987,-0.0],"angular_velocity":[-0.00067,0.00066,-0.0017]}]},{"frame_id":17,"trajectory":[{"object_id":0,"location":[-1.50307,-0.61605,0.3],"orientation":[0.3779,-0.0,0.0,0.72351],"velocity":[1.26606,-0.75171,-3e-05],"angular_velocity":[-0.0005,-0.00594,-144.96581]},{"object_id":1,"location":[-0.39052,-0.49097,0.4],"orientation":[0.83235,0.0,0.0,0.38191],"velocity":[-1.33081,-0.52495,-0.0],"angular_velocity":[0.00019,0.00042,-63.0856]},{"object_id":2,"location":[0.22338,1.63261,0.2],"orientation":[0.71467,0.0,0.0,-0.1665],"velocity":[0.64546,1.13435,-0.0],"angular_velocity":[0.0,0.0,-0.00156]}]},{"frame_id":18,"trajectory":[{"object_id":0,"location":[-1.46185,-0.64011,0.3],"orientation":[0.39954,-0.0,-0.0,0.70747],"velocity":[1.21188,-0.69861,-1e-05],"angular_velocity":[0.0,-0.00047,-140.15343]},{"object_id":1,"location":[-0.43357,-0.50778,0.4],"orientation":[0.83908,-0.0,0.0,0.3682],"velocity":[-1.261,-0.48848,-2e-05],"angular_velocity":[0.00156,0.00244,-60.72535]},{"object_id":2,"location":[0.24451,1.66976,0.2],"orientation":[0.71467,-0.0,-0.0,-0.1665],"velocity":[0.62524,1.09882,-0.0],"angular_velocity":[-0.00048,0.00057,-0.00159]}]},{"frame_id":19,"trajectory":[{"object_id":0,"location":[-1.42266,-0.6625,0.3],"orientation":[0.41957,0.0,-0.0,0.69087],"velocity":[1.14584,-0.65275,-1e-05],"angular_velocity":[-0.00013,-0.0017,-139.05043]},{"object_id":1,"location":[-0.4743,-0.5234,0.4],"orientation":[0.84529,0.0,-0.0,0.35497],"velocity":[-1.19026,-0.45458,-0.0],"angular_velocity":[-0.00079,5e-05,-57.316]},{"object_id":2,"location":[0.26497,1.70572,0.2],"orientation":[0.71467,-0.0,0.0,-0.1665],"velocity":[0.60503,1.06329,-1e-05],"angular_velocity":[-0.00071,0.00118,-0.00177]}]},{"frame_id":20,"trajectory":[{"object_id":0,"location":[-1.38586,-0.68367,0.3],"orientation":[0.43816,0.0,-0.0,0.6736],"velocity":[1.07117,-0.62465,-0.0],"angular_velocity":[-1e-05,-6e-05,-137.29802]},{"object_id":1,"location":[-0.51265,-0.53792,0.4],"orientation":[0.85089,-0.0,0.0,0.34247],"velocity":[-1.11983,-0.4208,-0.0],"angular_velocity":[-0.00016,1e-05,-53.59202]},{"object_id":2,"location":[0.28589,1.70536,0.2],"orientation":[0.7183,0.0,0.0,-0.15541],"velocity":[0.66288,-0.83627,-2e-05],"angular_velocity":[-0.00406,0.00315,125.3372]}]},{"frame_id":21,"trajectory":[{"object_id":0,"location":[-1.39504,-0.70533,0.3],"orientation":[0.43542,0.0,-0.0,0.67628],"velocity":[-0.92429,-0.65088,-0.0],"angular_velocity":[0.00024,-0.00029,97.02402]},{"object_id":1,"location":[-0.53887,-0.55092,0.4],"orientation":[0.85589,0.0,-0.0,0.33081],"velocity":[-0.61192,-0.36765,-1e-05],"angular_velocity":[1e-05,0.00141,-47.82405]},{"object_id":2,"location":[0.30759,1.67808,0.2],"orientation":[0.72345,-0.0,-0.0,-0.13779],"velocity":[0.6412,-0.80422,-0.0],"angular_velocity":[-0.00074,0.00047,117.66855]}]},{"frame_id":22,"trajectory":[{"object_id":0,"location":[-1.42473,-0.72611,0.3],"orientation":[0.4232,0.0,-0.0,0.68766],"velocity":[-0.86442,-0.60212,-0.0],"angular_velocity":[0.0,1e-05,86.5354]},{"object_id":1,"location":[-0.55799,-0.56258,0.4],"orientation":[0.85995,-0.0,0.0,0.32096],"velocity":[-0.54578,-0.33416,-0.0],"angular_velocity":[-0.00011,-0.00059,-39.06027]},{"object_id":2,"location":[0.32854,1.65187,0.2],"orientation":[0.72773,-0.0,-0.0,-0.12096],"velocity":[0.61873,-0.77231,-0.0],"angular_velocity":[-0.00075,0.00044,110.45803]}]},{"frame_id":23,"trajectory":[{"object_id":0,"location":[-1.45242,-0.74527,0.3],"orientation":[0.41189,0.0,-0.0,0.69746],"velocity":[-0.80458,-0.55334,0.0],"angular_velocity":[-0.00012,9e-05,76.22717]},{"object_id":1,"location":[-0.57512,-0.57288,0.4],"orientation":[0.86312,-0.0,-0.0,0.313],"velocity":[-0.4851,-0.29315,-0.0],"angular_velocity":[-0.00017,0.0001,-31.07398]},{"object_id":2,"location":[0.34873,1.62673,0.2],"orientation":[0.73123,-0.0,-0.0,-0.10493],"velocity":[0.59561,-0.74056,-0.0],"angular_velocity":[-0.0,-0.0,103.65961]}]},{"frame_id":24,"trajectory":[{"object_id":0,"location":[-1.47811,-0.7628,0.3],"orientation":[0.40165,-0.0,0.0,0.7058],"velocity":[-0.74448,-0.50473,-0.0],"angular_velocity":[-0.0001,5e-05,66.24609]},{"object_id":1,"location":[-0.59017,-0.58182,0.4],"orientation":[0.86556,-0.0,-0.0,0.30672],"velocity":[-0.42499,-0.24886,-1e-05],"angular_velocity":[0.00043,0.00052,-24.12573]},{"object_id":2,"location":[0.36814,1.60263,0.2],"orientation":[0.73406,-0.0,0.0,-0.08972],"velocity":[0.57195,-0.70896,-1e-05],"angular_velocity":[-0.00162,0.00071,97.2126]}]},{"frame_id":25,"trajectory":[{"object_id":0,"location":[-1.50179,-0.77872,0.3],"orientation":[0.39257,0.0,-0.0,0.71283],"velocity":[-0.68389,-0.45642,-0.0],"angular_velocity":[-7e-05,2e-05,56.69199]},{"object_id":1,"location":[-0.60303,-0.58946,0.4],"orientation":[0.86738,-0.0,0.0,0.30193],"velocity":[-0.35528,-0.2138,-1e-05],"angular_velocity":[-0.00072,0.00135,-17.94495]},{"object_id":2,"location":[0.38676,1.57959,0.2],"orientation":[0.73631,-0.0,0.0,-0.07534],"velocity":[0.54787,-0.67749,-0.0],"angular_velocity":[-0.0,-0.0,91.05721]}]},{"frame_id":26,"trajectory":[{"object_id":0,"location":[-1.52344,-0.79303,0.3],"orientation":[0.38471,0.0,0.0,0.71865],"velocity":[-0.62257,-0.40856,-0.0],"angular_velocity":[-4e-05,-0.0,47.68393]},{"object_id":1,"location":[-0.6136,-0.59586,0.4],"orientation":[0.86868,0.0,0.0,0.29845],"velocity":[-0.28912,-0.17251,-1e-05],"angular_velocity":[0.001,0.00119,-12.75121]},{"object_id":2,"location":[0.40456,1.5576,0.2],"orientation":[0.73806,-0.0,0.0,-0.06179],"velocity":[0.52345,-0.64614,-0.0],"angular_velocity":[-0.0,-0.0,85.14237]}]},{"frame_id":27,"trajectory":[{"object_id":0,"location":[-1.54303,-0.80577,0.3],"orientation":[0.37804,0.0,0.0,0.72341],"velocity":[-0.56029,-0.36131,-1e-05],"angular_velocity":[-0.00056,-0.00121,39.33067]},{"object_id":1,"location":[-0.62202,-0.60079,0.4],"orientation":[0.86956,0.0,-0.0,0.29606],"velocity":[-0.22264,-0.13041,-1e-05],"angular_velocity":[0.00089,0.0012,-8.36967]},{"object_id":2,"location":[0.42155,1.53664,0.2],"orientation":[0.73938,0.0,0.0,-0.04907],"velocity":[0.49875,-0.61491,-1e-05],"angular_velocity":[-0.00356,0.00095,79.42646]}]},{"frame_id":28,"trajectory":[{"object_id":0,"location":[-1.56052,-0.81693,0.3],"orientation":[0.37254,-0.0,0.0,0.72722],"velocity":[-0.49697,-0.31474,-6e-05],"angular_velocity":[-0.00107,-0.00515,31.67576]},{"object_id":1,"location":[-0.62813,-0.60441,0.4],"orientation":[0.87009,0.0,-0.0,0.29462],"velocity":[-0.15258,-0.09158,-0.0],"angular_velocity":[-0.0004,0.00023,-4.61241]},{"object_id":2,"location":[0.43771,1.51673,0.2],"orientation":[0.74034,-0.0,-0.0,-0.03718],"velocity":[0.47382,-0.58376,-0.0],"angular_velocity":[-0.0,-0.0,73.87518]}]},{"frame_id":29,"trajectory":[{"object_id":0,"location":[-1.57588,-0.82656,0.3],"orientation":[0.36812,0.0,-0.0,0.73021],"velocity":[-0.43247,-0.26898,-4e-05],"angular_velocity":[-0.0006,-0.00321,24.78574]},{"object_id":1,"location":[-0.63192,-0.60668,0.4],"orientation":[0.87035,-0.0,-0.0,0.29392],"velocity":[-0.08416,-0.04936,-1e-05],"angular_velocity":[-0.00034,-0.00121,-1.95649]},{"object_id":2,"location":[0.45303,1.49786,0.2],"orientation":[0.74099,-0.0,0.0,-0.02611],"velocity":[0.44873,-0.5527,-0.0],"angular_velocity":[-0.0,-0.0,68.46358]}]},{"frame_id":30,"trajectory":[{"object_id":0,"location":[-1.58907,-0.83469,0.3],"orientation":[0.36471,-0.0,0.0,0.73247],"velocity":[-0.36684,-0.22405,-2e-05],"angular_velocity":[-0.00019,-0.00209,18.65206]},{"object_id":1,"location":[-0.63343,-0.60755,0.4],"orientation":[0.87042,0.0,-0.0,0.29372],"velocity":[-0.01458,-0.0081,-0.0],"angular_velocity":[-3e-05,-0.0002,-0.20212]},{"object_id":2,"location":[0.46752,1.48001,0.2],"orientation":[0.74139,-0.0,0.0,-0.01586],"velocity":[0.42348,-0.52171,-0.0],"angular_velocity":[-1e-05,-0.0,63.17659]}]},{"frame_id":31,"trajectory":[{"object_id":0,"location":[-1.59336,-0.84144,0.3],"orientation":[0.36523,-0.0,0.0,0.73213],"velocity":[0.16246,-0.20017,-3e-05],"angular_velocity":[-0.00032,-0.00454,-21.73401]},{"object_id":1,"location":[-0.63346,-0.60756,0.4],"orientation":[0.87042,-0.0,0.0,0.29372],"velocity":[3e-05,-2e-05,-2e-05],"angular_velocity":[0.00149,-0.00039,7e-05]},{"object_id":2,"location":[0.48116,1.4632,0.2],"orientation":[0.74158,-0.0,-0.0,-0.00641],"velocity":[0.39811,-0.49077,-0.0],"angular_velocity":[-3e-05,-1e-05,58.00154]}]},{"frame_id":32,"trajectory":[{"object_id":0,"location":[-1.58862,-0.84692,0.3],"orientation":[0.36779,-0.0,0.0,0.73043],"velocity":[0.12472,-0.13684,-1e-05],"angular_velocity":[-0.00018,-0.0013,-12.15849]},{"object_id":1,"location":[-0.63346,-0.60756,0.4],"orientation":[0.87042,-0.0,0.0,0.29372],"velocity":[3e-05,-2e-05,-1e-05],"angular_velocity":[0.00177,0.00145,-4e-05]},{"object_id":2,"location":[0.49395,1.44742,0.2],"orientation":[0.74162,0.0,-0.0,0.00223],"velocity":[0.37265,-0.45986,-0.0],"angular_velocity":[-0.00097,7e-05,52.93709]}]},{"frame_id":33,"trajectory":[{"object_id":0,"location":[-1.58532,-0.85033,0.3],"orientation":[0.36913,-0.0,0.0,0.72953],"velocity":[0.07771,-0.0759,-3e-05],"angular_velocity":[-0.00054,-0.00464,-5.93784]},{"object_id":1,"location":[-0.63346,-0.60756,0.4],"orientation":[0.87042,-0.0,0.0,0.29372],"velocity":[3e-05,-2e-05,-1e-05],"angular_velocity":[0.00148,0.00055,-4e-05]},{"object_id":2,"location":[0.50589,1.43268,0.2],"orientation":[0.74153,-0.0,0.0,0.01009],"velocity":[0.34711,-0.42898,-0.0],"angular_velocity":[-0.00092,7e-05,47.98191]}]},{"frame_id":34,"trajectory":[{"object_id":0,"location":[-1.58373,-0.85179,0.3],"orientation":[0.36967,-0.0,0.0,0.72917],"velocity":[0.02349,-0.01904,-1e-05],"angular_velocity":[-0.00108,0.0001,-1.58694]},{"object_id":1,"location":[-0.63346,-0.60756,0.4],"orientation":[0.87042,-0.0,0.0,0.29372],"velocity":[3e-05,-1e-05,-1e-05],"angular_velocity":[0.00144,0.00106,-3e-05]},{"object_id":2,"location":[0.51698,1.41895,0.2],"orientation":[0.74135,-0.0,0.0,0.01718],"velocity":[0.32153,-0.3981,0.0],"angular_velocity":[0.0,-0.0,43.13865]}]},{"frame_id":35,"trajectory":[{"object_id":0,"location":[-1.58362,-0.85187,0.3],"orientation":[0.3697,-0.0,-0.0,0.72915],"velocity":[-0.00013,0.00011,-4e-05],"angular_velocity":[-0.01248,-0.01475,7e-05]},{"object_id":1,"location":[-0.63346,-0.60756,0.4],"orientation":[0.87042,-0.0,-0.0,0.29372],"velocity":[2e-05,-2e-05,-2e-05],"angular_velocity":[0.00147,-0.00041,0.0002]},{"object_id":2,"location":[0.52722,1.40626,0.2],"orientation":[0.74111,0.0,0.0,0.02352],"velocity":[0.29592,-0.3672,-0.0],"angular_velocity":[-0.00096,2e-05,38.42366]}]},{"frame_id":36,"trajectory":[{"object_id":0,"location":[-1.58362,-0.85187,0.3],"orientation":[0.3697,-0.0,-0.0,0.72915],"velocity":[-0.0002,-4e-05,-3e-05],"angular_velocity":[0.00824,-0.01946,-0.00099]},{"object_id":1,"location":[-0.63346,-0.60756,0.4],"orientation":[0.87042,-0.0,-0.0,0.29372],"velocity":[2e-05,-2e-05,-1e-05],"angular_velocity":[0.00161,0.00081,1e-05]},{"object_id":2,"location":[0.5366,1.3946,0.2],"orientation":[0.74083,-0.0,-0.0,0.02912],"velocity":[0.27029,-0.33628,-1e-05],"angular_velocity":[-0.00193,-1e-05,33.84495]}]},{"frame_id":37,"trajectory":[{"object_id":0,"location":[-1.58362,-0.85187,0.3],"orientation":[0.3697,-0.0,-0.0,0.72915],"velocity":[-0.00014,0.00011,-4e-05],"angular_velocity":[-0.01166,-0.01569,0.00055]},{"object_id":1,"location":[-0.63346,-0.60756,0.4],"orientation":[0.87042,-0.0,0.0,0.29372],"velocity":[4e-05,-2e-05,-1e-05],"angular_velocity":[0.00207,0.00189,-8e-05]},{"object_id":2,"location":[0.54513,1.38397,0.2],"orientation":[0.74055,-0.0,0.0,0.03402],"velocity":[0.24466,-0.30529,0.0],"angular_velocity":[2e-05,1e-05,29.41982]}]},{"frame_id":38,"trajectory":[{"object_id":0,"location":[-1.58362,-0.85187,0.3],"orientation":[0.3697,-0.0,-0.0,0.72915],"velocity":[-0.00018,0.00012,-4e-05],"angular_velocity":[-0.01402,-0.01732,-0.00026]},{"object_id":1,"location":[-0.63346,-0.60756,0.4],"orientation":[0.87042,-0.0,0.0,0.29372],"velocity":[4e-05,-2e-05,-1e-05],"angular_velocity":[0.00207,0.00189,-8e-05]},{"object_id":2,"location":[0.55281,1.37438,0.2],"orientation":[0.74026,0.0,-0.0,0.03823],"velocity":[0.21906,-0.27424,-0.0],"angular_velocity":[-2e-05,-1e-05,25.16379]}]},{"frame_id":39,"trajectory":[{"object_id":0,"location":[-1.58362,-0.85187,0.3],"orientation":[0.3697,-0.0,-0.0,0.72915],"velocity":[-0.00015,0.00011,-4e-05],"angular_velocity":[-0.01251,-0.0157,0.00037]},{"object_id":1,"location":[-0.63346,-0.60756,0.4],"orientation":[0.87042,-0.0,0.0,0.29372],"velocity":[4e-05,-2e-05,-1e-05],"angular_velocity":[0.00207,0.00189,-8e-05]},{"object_id":2,"location":[0.55963,1.36582,0.2],"orientation":[0.74,0.0,-0.0,0.0418],"velocity":[0.19348,-0.24309,-0.0],"angular_velocity":[-2e-05,-1e-05,21.09946]}]},{"frame_id":40,"trajectory":[{"object_id":0,"location":[-1.58362,-0.85187,0.3],"orientation":[0.3697,-0.0,-0.0,0.72915],"velocity":[-0.00013,0.0001,-5e-05],"angular_velocity":[-0.01028,-0.01626,0.00019]},{"object_id":1,"location":[-0.63346,-0.60756,0.4],"orientation":[0.87042,-0.0,0.0,0.29372],"velocity":[4e-05,-2e-05,-1e-05],"angular_velocity":[0.00207,0.00189,-8e-05]},{"object_id":2,"location":[0.5656,1.35831,0.2],"orientation":[0.73976,-0.0,0.0,0.04474],"velocity":[0.16795,-0.21184,-0.0],"angular_velocity":[-0.0,0.0,17.25562]}]},{"frame_id":41,"trajectory":[{"object_id":0,"location":[-1.58362,-0.85187,0.3],"orientation":[0.3697,-0.0,-0.0,0.72915],"velocity":[-0.00016,0.0001,-5e-05],"angular_velocity":[-0.01108,-0.01705,0.00044]},{"object_id":1,"location":[-0.63346,-0.60756,0.4],"orientation":[0.87042,-0.0,0.0,0.29372],"velocity":[4e-05,-2e-05,-1e-05],"angular_velocity":[0.00207,0.00189,-8e-05]},{"object_id":2,"location":[0.57072,1.35183,0.2],"orientation":[0.73956,-0.0,0.0,0.04711],"velocity":[0.14248,-0.18046,-0.0],"angular_velocity":[-0.00098,-7e-05,13.64261]}]},{"frame_id":42,"trajectory":[{"object_id":0,"location":[-1.58362,-0.85187,0.3],"orientation":[0.3697,-0.0,-0.0,0.72915],"velocity":[-0.00016,0.0001,-5e-05],"angular_velocity":[-0.01108,-0.01705,0.00044]},{"object_id":1,"location":[-0.63346,-0.60756,0.4],"orientation":[0.87042,-0.0,0.0,0.29372],"velocity":[4e-05,-2e-05,-1e-05],"angular_velocity":[0.00207,0.00189,-8e-05]},{"object_id":2,"location":[0.57499,1.34641,0.2],"orientation":[0.73939,-0.0,-0.0,0.04893],"velocity":[0.11708,-0.14895,-1e-05],"angular_velocity":[-0.00191,-0.0001,10.30181]}]},{"frame_id":43,"trajectory":[{"object_id":0,"location":[-1.58362,-0.85187,0.3],"orientation":[0.3697,-0.0,-0.0,0.72915],"velocity":[-0.00016,0.0001,-5e-05],"angular_velocity":[-0.01108,-0.01705,0.00044]},{"object_id":1,"location":[-0.63346,-0.60756,0.4],"orientation":[0.87042,-0.0,0.0,0.29372],"velocity":[4e-05,-2e-05,-1e-05],"angular_velocity":[0.00207,0.00189,-8e-05]},{"object_id":2,"location":[0.57842,1.34204,0.2],"orientation":[0.73927,-0.0,0.0,0.05026],"velocity":[0.09176,-0.11729,-0.0],"angular_velocity":[-0.0,-0.0,7.26704]}]},{"frame_id":44,"trajectory":[{"object_id":0,"location":[-1.58362,-0.85187,0.3],"orientation":[0.3697,-0.0,-0.0,0.72915],"velocity":[-0.00016,0.0001,-5e-05],"angular_velocity":[-0.01108,-0.01705,0.00044]},{"object_id":1,"location":[-0.63346,-0.60756,0.4],"orientation":[0.87042,-0.0,0.0,0.29372],"velocity":[4e-05,-2e-05,-1e-05],"angular_velocity":[0.00207,0.00189,-8e-05]},{"object_id":2,"location":[0.58101,1.33872,0.2],"orientation":[0.73919,0.0,0.0,0.05114],"velocity":[0.06653,-0.08546,-0.0],"angular_velocity":[-1e-05,-0.0,4.59191]}]},{"frame_id":45,"trajectory":[{"object_id":0,"location":[-1.58362,-0.85187,0.3],"orientation":[0.3697,-0.0,-0.0,0.72915],"velocity":[-0.00016,0.0001,-5e-05],"angular_velocity":[-0.01108,-0.01705,0.00044]},{"object_id":1,"location":[-0.63346,-0.60756,0.4],"orientation":[0.87042,-0.0,0.0,0.29372],"velocity":[4e-05,-2e-05,-1e-05],"angular_velocity":[0.00207,0.00189,-8e-05]},{"object_id":2,"location":[0.58275,1.33647,0.2],"orientation":[0.73914,0.0,-0.0,0.05165],"velocity":[0.04139,-0.05346,-0.0],"angular_velocity":[4e-05,5e-05,2.32997]}]},{"frame_id":46,"trajectory":[{"object_id":0,"location":[-1.58362,-0.85187,0.3],"orientation":[0.3697,-0.0,-0.0,0.72915],"velocity":[-0.00016,0.0001,-5e-05],"angular_velocity":[-0.01108,-0.01705,0.00044]},{"object_id":1,"location":[-0.63346,-0.60756,0.4],"orientation":[0.87042,-0.0,0.0,0.29372],"velocity":[4e-05,-2e-05,-1e-05],"angular_velocity":[0.00207,0.00189,-8e-05]},{"object_id":2,"location":[0.58366,1.33529,0.2],"orientation":[0.73912,0.0,0.0,0.05184],"velocity":[0.01637,-0.02127,-0.0],"angular_velocity":[1e-05,-0.0,0.63317]}]},{"frame_id":47,"trajectory":[{"object_id":0,"location":[-1.58362,-0.85187,0.3],"orientation":[0.3697,-0.0,-0.0,0.72915],"velocity":[-0.00016,0.0001,-5e-05],"angular_velocity":[-0.01108,-0.01705,0.00044]},{"object_id":1,"location":[-0.63346,-0.60756,0.4],"orientation":[0.87042,-0.0,0.0,0.29372],"velocity":[4e-05,-2e-05,-1e-05],"angular_velocity":[0.00207,0.00189,-8e-05]},{"object_id":2,"location":[0.58381,1.3351,0.2],"orientation":[0.73912,-0.0,0.0,0.05186],"velocity":[7e-05,8e-05,-5e-05],"angular_velocity":[-0.01854,0.00973,-0.00029]}]},{"frame_id":48,"trajectory":[{"object_id":0,"location":[-1.58362,-0.85187,0.3],"orientation":[0.3697,-0.0,-0.0,0.72915],"velocity":[-0.00016,0.0001,-5e-05],"angular_velocity":[-0.01108,-0.01705,0.00044]},{"object_id":1,"location":[-0.63346,-0.60756,0.4],"orientation":[0.87042,-0.0,0.0,0.29372],"velocity":[4e-05,-2e-05,-1e-05],"angular_velocity":[0.00207,0.00189,-8e-05]},{"object_id":2,"location":[0.58381,1.3351,0.2],"orientation":[0.73912,-0.0,0.0,0.05186],"velocity":[6e-05,8e-05,-5e-05],"angular_velocity":[-0.01885,0.00819,-0.00024]}]},{"frame_id":49,"trajectory":[{"object_id":0,"location":[-1.58362,-0.85187,0.3],"orientation":[0.3697,-0.0,-0.0,0.72915],"velocity":[-0.00016,0.0001,-5e-05],"angular_velocity":[-0.01108,-0.01705,0.00044]},{"object_id":1,"location":[-0.63346,-0.60756,0.4],"orientation":[0.87042,-0.0,0.0,0.29372],"velocity":[4e-05,-2e-05,-1e-05],"angular_velocity":[0.00207,0.00189,-8e-05]},{"object_id":2,"location":[0.58381,1.3351,0.2],"orientation":[0.73912,-0.0,0.0,0.05186],"velocity":[6e-05,8e-05,-5e-05],"angular_velocity":[-0.01959,0.00855,0.00013]}]},{"frame_id":50,"trajectory":[{"object_id":0,"location":[-1.58362,-0.85187,0.3],"orientation":[0.3697,-0.0,-0.0,0.72915],"velocity":[-0.00016,0.0001,-5e-05],"angular_velocity":[-0.01108,-0.01705,0.00044]},{"object_id":1,"location":[-0.63346,-0.60756,0.4],"orientation":[0.87042,-0.0,0.0,0.29372],"velocity":[4e-05,-2e-05,-1e-05],"angular_velocity":[0.00207,0.00189,-8e-05]},{"object_id":2,"location":[0.58381,1.3351,0.2],"orientation":[0.73912,-0.0,0.0,0.05186],"velocity":[6e-05,8e-05,-5e-05],"angular_velocity":[-0.01939,0.00773,-0.00028]}]},{"frame_id":51,"trajectory":[{"object_id":0,"location":[-1.58362,-0.85187,0.3],"orientation":[0.3697,-0.0,-0.0,0.72915],"velocity":[-0.00016,0.0001,-5e-05],"angular_velocity":[-0.01108,-0.01705,0.00044]},{"object_id":1,"location":[-0.63346,-0.60756,0.4],"orientation":[0.87042,-0.0,0.0,0.29372],"velocity":[4e-05,-2e-05,-1e-05],"angular_velocity":[0.00207,0.00189,-8e-05]},{"object_id":2,"location":[0.58381,1.3351,0.2],"orientation":[0.73912,-0.0,0.0,0.05186],"velocity":[6e-05,8e-05,-5e-05],"angular_velocity":[-0.01878,0.00783,-0.00027]}]},{"frame_id":52,"trajectory":[{"object_id":0,"location":[-1.58362,-0.85187,0.3],"orientation":[0.3697,-0.0,-0.0,0.72915],"velocity":[-0.00016,0.0001,-5e-05],"angular_velocity":[-0.01108,-0.01705,0.00044]},{"object_id":1,"location":[-0.63346,-0.60756,0.4],"orientation":[0.87042,-0.0,0.0,0.29372],"velocity":[4e-05,-2e-05,-1e-05],"angular_velocity":[0.00207,0.00189,-8e-05]},{"object_id":2,"location":[0.58381,1.3351,0.2],"orientation":[0.73912,-0.0,0.0,0.05186],"velocity":[6e-05,8e-05,-5e-05],"angular_velocity":[-0.01882,0.00821,-0.00035]}]},{"frame_id":53,"trajectory":[{"object_id":0,"location":[-1.58362,-0.85187,0.3],"orientation":[0.3697,-0.0,-0.0,0.72915],"velocity":[-0.00016,0.0001,-5e-05],"angular_velocity":[-0.01108,-0.01705,0.00044]},{"object_id":1,"location":[-0.63346,-0.60756,0.4],"orientation":[0.87042,-0.0,0.0,0.29372],"velocity":[4e-05,-2e-05,-1e-05],"angular_velocity":[0.00207,0.00189,-8e-05]},{"object_id":2,"location":[0.58381,1.3351,0.2],"orientation":[0.73912,-0.0,0.0,0.05186],"velocity":[5e-05,0.0001,-5e-05],"angular_velocity":[-0.0208,0.0069,-0.00047]}]},{"frame_id":54,"trajectory":[{"object_id":0,"location":[-1.58362,-0.85187,0.3],"orientation":[0.3697,-0.0,-0.0,0.72915],"velocity":[-0.00016,0.0001,-5e-05],"angular_velocity":[-0.01108,-0.01705,0.00044]},{"object_id":1,"location":[-0.63346,-0.60756,0.4],"orientation":[0.87042,-0.0,0.0,0.29372],"velocity":[4e-05,-2e-05,-1e-05],"angular_velocity":[0.00207,0.00189,-8e-05]},{"object_id":2,"location":[0.58381,1.3351,0.2],"orientation":[0.73912,-0.0,0.0,0.05186],"velocity":[5e-05,0.0001,-5e-05],"angular_velocity":[-0.0208,0.0069,-0.00047]}]},{"frame_id":55,"trajectory":[{"object_id":0,"location":[-1.58362,-0.85187,0.3],"orientation":[0.3697,-0.0,-0.0,0.72915],"velocity":[-0.00016,0.0001,-5e-05],"angular_velocity":[-0.01108,-0.01705,0.00044]},{"object_id":1,"location":[-0.63346,-0.60756,0.4],"orientation":[0.87042,-0.0,0.0,0.29372],"velocity":[4e-05,-2e-05,-1e-05],"angular_velocity":[0.00207,0.00189,-8e-05]},{"object_id":2,"location":[0.58381,1.3351,0.2],"orientation":[0.73912,-0.0,0.0,0.05186],"velocity":[5e-05,0.0001,-5e-05],"angular_velocity":[-0.0208,0.0069,-0.00047]}]},{"frame_id":56,"trajectory":[{"object_id":0,"location":[-1.58362,-0.85187,0.3],"orientation":[0.3697,-0.0,-0.0,0.72915],"velocity":[-0.00016,0.0001,-5e-05],"angular_velocity":[-0.01108,-0.01705,0.00044]},{"object_id":1,"location":[-0.63346,-0.60756,0.4],"orientation":[0.87042,-0.0,0.0,0.29372],"velocity":[4e-05,-2e-05,-1e-05],"angular_velocity":[0.00207,0.00189,-8e-05]},{"object_id":2,"location":[0.58381,1.3351,0.2],"orientation":[0.73912,-0.0,0.0,0.05186],"velocity":[5e-05,0.0001,-5e-05],"angular_velocity":[-0.0208,0.0069,-0.00047]}]},{"frame_id":57,"trajectory":[{"object_id":0,"location":[-1.58362,-0.85187,0.3],"orientation":[0.3697,-0.0,-0.0,0.72915],"velocity":[-0.00016,0.0001,-5e-05],"angular_velocity":[-0.01108,-0.01705,0.00044]},{"object_id":1,"location":[-0.63346,-0.60756,0.4],"orientation":[0.87042,-0.0,0.0,0.29372],"velocity":[4e-05,-2e-05,-1e-05],"angular_velocity":[0.00207,0.00189,-8e-05]},{"object_id":2,"location":[0.58381,1.3351,0.2],"orientation":[0.73912,-0.0,0.0,0.05186],"velocity":[5e-05,0.0001,-5e-05],"angular_velocity":[-0.0208,0.0069,-0.00047]}]},{"frame_id":58,"trajectory":[{"object_id":0,"location":[-1.58362,-0.85187,0.3],"orientation":[0.3697,-0.0,-0.0,0.72915],"velocity":[-0.00016,0.0001,-5e-05],"angular_velocity":[-0.01108,-0.01705,0.00044]},{"object_id":1,"location":[-0.63346,-0.60756,0.4],"orientation":[0.87042,-0.0,0.0,0.29372],"velocity":[4e-05,-2e-05,-1e-05],"angular_velocity":[0.00207,0.00189,-8e-05]},{"object_id":2,"location":[0.58381,1.3351,0.2],"orientation":[0.73912,-0.0,0.0,0.05186],"velocity":[5e-05,0.0001,-5e-05],"angular_velocity":[-0.0208,0.0069,-0.00047]}]},{"frame_id":59,"trajectory":[{"object_id":0,"location":[-1.58362,-0.85187,0.3],"orientation":[0.3697,-0.0,-0.0,0.72915],"velocity":[-0.00016,0.0001,-5e-05],"angular_velocity":[-0.01108,-0.01705,0.00044]},{"object_id":1,"location":[-0.63346,-0.60756,0.4],"orientation":[0.87042,-0.0,0.0,0.29372],"velocity":[4e-05,-2e-05,-1e-05],"angular_velocity":[0.00207,0.00189,-8e-05]},{"object_id":2,"location":[0.58381,1.3351,0.2],"orientation":[0.73912,-0.0,0.0,0.05186],"velocity":[5e-05,0.0001,-5e-05],"angular_velocity":[-0.0208,0.0069,-0.00047]}]},{"frame_id":60,"trajectory":[{"object_id":0,"location":[-1.58362,-0.85187,0.3],"orientation":[0.3697,-0.0,-0.0,0.72915],"velocity":[-0.00016,0.0001,-5e-05],"angular_velocity":[-0.01108,-0.01705,0.00044]},{"object_id":1,"location":[-0.63346,-0.60756,0.4],"orientation":[0.87042,-0.0,0.0,0.29372],"velocity":[4e-05,-2e-05,-1e-05],"angular_velocity":[0.00207,0.00189,-8e-05]},{"object_id":2,"location":[0.58381,1.3351,0.2],"orientation":[0.73912,-0.0,0.0,0.05186],"velocity":[5e-05,0.0001,-5e-05],"angular_velocity":[-0.0208,0.0069,-0.00047]}]},{"frame_id":61,"trajectory":[{"object_id":0,"location":[-1.58362,-0.85187,0.3],"orientation":[0.3697,-0.0,-0.0,0.72915],"velocity":[-0.00016,0.0001,-5e-05],"angular_velocity":[-0.01108,-0.01705,0.00044]},{"object_id":1,"location":[-0.63346,-0.60756,0.4],"orientation":[0.87042,-0.0,0.0,0.29372],"velocity":[4e-05,-2e-05,-1e-05],"angular_velocity":[0.00207,0.00189,-8e-05]},{"object_id":2,"location":[0.58381,1.3351,0.2],"orientation":[0.73912,-0.0,0.0,0.05186],"velocity":[5e-05,0.0001,-5e-05],"angular_velocity":[-0.0208,0.0069,-0.00047]}]},{"frame_id":62,"trajectory":[{"object_id":0,"location":[-1.58362,-0.85187,0.3],"orientation":[0.3697,-0.0,-0.0,0.72915],"velocity":[-0.00016,0.0001,-5e-05],"angular_velocity":[-0.01108,-0.01705,0.00044]},{"object_id":1,"location":[-0.63346,-0.60756,0.4],"orientation":[0.87042,-0.0,0.0,0.29372],"velocity":[4e-05,-2e-05,-1e-05],"angular_velocity":[0.00207,0.00189,-8e-05]},{"object_id":2,"location":[0.58381,1.3351,0.2],"orientation":[0.73912,-0.0,0.0,0.05186],"velocity":[5e-05,0.0001,-5e-05],"angular_velocity":[-0.0208,0.0069,-0.00047]}]},{"frame_id":63,"trajectory":[{"object_id":0,"location":[-1.58362,-0.85187,0.3],"orientation":[0.3697,-0.0,-0.0,0.72915],"velocity":[-0.00016,0.0001,-5e-05],"angular_velocity":[-0.01108,-0.01705,0.00044]},{"object_id":1,"location":[-0.63346,-0.60756,0.4],"orientation":[0.87042,-0.0,0.0,0.29372],"velocity":[4e-05,-2e-05,-1e-05],"angular_velocity":[0.00207,0.00189,-8e-05]},{"object_id":2,"location":[0.58381,1.3351,0.2],"orientation":[0.73912,-0.0,0.0,0.05186],"velocity":[5e-05,0.0001,-5e-05],"angular_velocity":[-0.0208,0.0069,-0.00047]}]},{"frame_id":64,"trajectory":[{"object_id":0,"location":[-1.58362,-0.85187,0.3],"orientation":[0.3697,-0.0,-0.0,0.72915],"velocity":[-0.00016,0.0001,-5e-05],"angular_velocity":[-0.01108,-0.01705,0.00044]},{"object_id":1,"location":[-0.63346,-0.60756,0.4],"orientation":[0.87042,-0.0,0.0,0.29372],"velocity":[4e-05,-2e-05,-1e-05],"angular_velocity":[0.00207,0.00189,-8e-05]},{"object_id":2,"location":[0.58381,1.3351,0.2],"orientation":[0.73912,-0.0,0.0,0.05186],"velocity":[5e-05,0.0001,-5e-05],"angular_velocity":[-0.0208,0.0069,-0.00047]}]},{"frame_id":65,"trajectory":[{"object_id":0,"location":[-1.58362,-0.85187,0.3],"orientation":[0.3697,-0.0,-0.0,0.72915],"velocity":[-0.00016,0.0001,-5e-05],"angular_velocity":[-0.01108,-0.01705,0.00044]},{"object_id":1,"location":[-0.63346,-0.60756,0.4],"orientation":[0.87042,-0.0,0.0,0.29372],"velocity":[4e-05,-2e-05,-1e-05],"angular_velocity":[0.00207,0.00189,-8e-05]},{"object_id":2,"location":[0.58381,1.3351,0.2],"orientation":[0.73912,-0.0,0.0,0.05186],"velocity":[5e-05,0.0001,-5e-05],"angular_velocity":[-0.0208,0.0069,-0.00047]}]},{"frame_id":66,"trajectory":[{"object_id":0,"location":[-1.58362,-0.85187,0.3],"orientation":[0.3697,-0.0,-0.0,0.72915],"velocity":[-0.00016,0.0001,-5e-05],"angular_velocity":[-0.01108,-0.01705,0.00044]},{"object_id":1,"location":[-0.63346,-0.60756,0.4],"orientation":[0.87042,-0.0,0.0,0.29372],"velocity":[4e-05,-2e-05,-1e-05],"angular_velocity":[0.00207,0.00189,-8e-05]},{"object_id":2,"location":[0.58381,1.3351,0.2],"orientation":[0.73912,-0.0,0.0,0.05186],"velocity":[5e-05,0.0001,-5e-05],"angular_velocity":[-0.0208,0.0069,-0.00047]}]},{"frame_id":67,"trajectory":[{"object_id":0,"location":[-1.58362,-0.85187,0.3],"orientation":[0.3697,-0.0,-0.0,0.72915],"velocity":[-0.00016,0.0001,-5e-05],"angular_velocity":[-0.01108,-0.01705,0.00044]},{"object_id":1,"location":[-0.63346,-0.60756,0.4],"orientation":[0.87042,-0.0,0.0,0.29372],"velocity":[4e-05,-2e-05,-1e-05],"angular_velocity":[0.00207,0.00189,-8e-05]},{"object_id":2,"location":[0.58381,1.3351,0.2],"orientation":[0.73912,-0.0,0.0,0.05186],"velocity":[5e-05,0.0001,-5e-05],"angular_velocity":[-0.0208,0.0069,-0.00047]}]},{"frame_id":68,"trajectory":[{"object_id":0,"location":[-1.58362,-0.85187,0.3],"orientation":[0.3697,-0.0,-0.0,0.72915],"velocity":[-0.00016,0.0001,-5e-05],"angular_velocity":[-0.01108,-0.01705,0.00044]},{"object_id":1,"location":[-0.63346,-0.60756,0.4],"orientation":[0.87042,-0.0,0.0,0.29372],"velocity":[4e-05,-2e-05,-1e-05],"angular_velocity":[0.00207,0.00189,-8e-05]},{"object_id":2,"location":[0.58381,1.3351,0.2],"orientation":[0.73912,-0.0,0.0,0.05186],"velocity":[5e-05,0.0001,-5e-05],"angular_velocity":[-0.0208,0.0069,-0.00047]}]},{"frame_id":69,"trajectory":[{"object_id":0,"location":[-1.58362,-0.85187,0.3],"orientation":[0.3697,-0.0,-0.0,0.72915],"velocity":[-0.00016,0.0001,-5e-05],"angular_velocity":[-0.01108,-0.01705,0.00044]},{"object_id":1,"location":[-0.63346,-0.60756,0.4],"orientation":[0.87042,-0.0,0.0,0.29372],"velocity":[4e-05,-2e-05,-1e-05],"angular_velocity":[0.00207,0.00189,-8e-05]},{"object_id":2,"location":[0.58381,1.3351,0.2],"orientation":[0.73912,-0.0,0.0,0.05186],"velocity":[5e-05,0.0001,-5e-05],"angular_velocity":[-0.0208,0.0069,-0.00047]}]},{"frame_id":70,"trajectory":[{"object_id":0,"location":[-1.58362,-0.85187,0.3],"orientation":[0.3697,-0.0,-0.0,0.72915],"velocity":[-0.00016,0.0001,-5e-05],"angular_velocity":[-0.01108,-0.01705,0.00044]},{"object_id":1,"location":[-0.63346,-0.60756,0.4],"orientation":[0.87042,-0.0,0.0,0.29372],"velocity":[4e-05,-2e-05,-1e-05],"angular_velocity":[0.00207,0.00189,-8e-05]},{"object_id":2,"location":[0.58381,1.3351,0.2],"orientation":[0.73912,-0.0,0.0,0.05186],"velocity":[5e-05,0.0001,-5e-05],"angular_velocity":[-0.0208,0.0069,-0.00047]}]},{"frame_id":71,"trajectory":[{"object_id":0,"location":[-1.58362,-0.85187,0.3],"orientation":[0.3697,-0.0,-0.0,0.72915],"velocity":[-0.00016,0.0001,-5e-05],"angular_velocity":[-0.01108,-0.01705,0.00044]},{"object_id":1,"location":[-0.63346,-0.60756,0.4],"orientation":[0.87042,-0.0,0.0,0.29372],"velocity":[4e-05,-2e-05,-1e-05],"angular_velocity":[0.00207,0.00189,-8e-05]},{"object_id":2,"location":[0.58381,1.3351,0.2],"orientation":[0.73912,-0.0,0.0,0.05186],"velocity":[5e-05,0.0001,-5e-05],"angular_velocity":[-0.0208,0.0069,-0.00047]}]},{"frame_id":72,"trajectory":[{"object_id":0,"location":[-1.58362,-0.85187,0.3],"orientation":[0.3697,-0.0,-0.0,0.72915],"velocity":[-0.00016,0.0001,-5e-05],"angular_velocity":[-0.01108,-0.01705,0.00044]},{"object_id":1,"location":[-0.63346,-0.60756,0.4],"orientation":[0.87042,-0.0,0.0,0.29372],"velocity":[4e-05,-2e-05,-1e-05],"angular_velocity":[0.00207,0.00189,-8e-05]},{"object_id":2,"location":[0.58381,1.3351,0.2],"orientation":[0.73912,-0.0,0.0,0.05186],"velocity":[5e-05,0.0001,-5e-05],"angular_velocity":[-0.0208,0.0069,-0.00047]}]},{"frame_id":73,"trajectory":[{"object_id":0,"location":[-1.58362,-0.85187,0.3],"orientation":[0.3697,-0.0,-0.0,0.72915],"velocity":[-0.00016,0.0001,-5e-05],"angular_velocity":[-0.01108,-0.01705,0.00044]},{"object_id":1,"location":[-0.63346,-0.60756,0.4],"orientation":[0.87042,-0.0,0.0,0.29372],"velocity":[4e-05,-2e-05,-1e-05],"angular_velocity":[0.00207,0.00189,-8e-05]},{"object_id":2,"location":[0.58381,1.3351,0.2],"orientation":[0.73912,-0.0,0.0,0.05186],"velocity":[5e-05,0.0001,-5e-05],"angular_velocity":[-0.0208,0.0069,-0.00047]}]},{"frame_id":74,"trajectory":[{"object_id":0,"location":[-1.58362,-0.85187,0.3],"orientation":[0.3697,-0.0,-0.0,0.72915],"velocity":[-0.00016,0.0001,-5e-05],"angular_velocity":[-0.01108,-0.01705,0.00044]},{"object_id":1,"location":[-0.63346,-0.60756,0.4],"orientation":[0.87042,-0.0,0.0,0.29372],"velocity":[4e-05,-2e-05,-1e-05],"angular_velocity":[0.00207,0.00189,-8e-05]},{"object_id":2,"location":[0.58381,1.3351,0.2],"orientation":[0.73912,-0.0,0.0,0.05186],"velocity":[5e-05,0.0001,-5e-05],"angular_velocity":[-0.0208,0.0069,-0.00047]}]},{"frame_id":75,"trajectory":[{"object_id":0,"location":[-1.58362,-0.85187,0.3],"orientation":[0.3697,-0.0,-0.0,0.72915],"velocity":[-0.00016,0.0001,-5e-05],"angular_velocity":[-0.01108,-0.01705,0.00044]},{"object_id":1,"location":[-0.63346,-0.60756,0.4],"orientation":[0.87042,-0.0,0.0,0.29372],"velocity":[4e-05,-2e-05,-1e-05],"angular_velocity":[0.00207,0.00189,-8e-05]},{"object_id":2,"location":[0.58381,1.3351,0.2],"orientation":[0.73912,-0.0,0.0,0.05186],"velocity":[5e-05,0.0001,-5e-05],"angular_velocity":[-0.0208,0.0069,-0.00047]}]},{"frame_id":76,"trajectory":[{"object_id":0,"location":[-1.58362,-0.85187,0.3],"orientation":[0.3697,-0.0,-0.0,0.72915],"velocity":[-0.00016,0.0001,-5e-05],"angular_velocity":[-0.01108,-0.01705,0.00044]},{"object_id":1,"location":[-0.63346,-0.60756,0.4],"orientation":[0.87042,-0.0,0.0,0.29372],"velocity":[4e-05,-2e-05,-1e-05],"angular_velocity":[0.00207,0.00189,-8e-05]},{"object_id":2,"location":[0.58381,1.3351,0.2],"orientation":[0.73912,-0.0,0.0,0.05186],"velocity":[5e-05,0.0001,-5e-05],"angular_velocity":[-0.0208,0.0069,-0.00047]}]},{"frame_id":77,"trajectory":[{"object_id":0,"location":[-1.58362,-0.85187,0.3],"orientation":[0.3697,-0.0,-0.0,0.72915],"velocity":[-0.00016,0.0001,-5e-05],"angular_velocity":[-0.01108,-0.01705,0.00044]},{"object_id":1,"location":[-0.63346,-0.60756,0.4],"orientation":[0.87042,-0.0,0.0,0.29372],"velocity":[4e-05,-2e-05,-1e-05],"angular_velocity":[0.00207,0.00189,-8e-05]},{"object_id":2,"location":[0.58381,1.3351,0.2],"orientation":[0.73912,-0.0,0.0,0.05186],"velocity":[5e-05,0.0001,-5e-05],"angular_velocity":[-0.0208,0.0069,-0.00047]}]},{"frame_id":78,"trajectory":[{"object_id":0,"location":[-1.58362,-0.85187,0.3],"orientation":[0.3697,-0.0,-0.0,0.72915],"velocity":[-0.00016,0.0001,-5e-05],"angular_velocity":[-0.01108,-0.01705,0.00044]},{"object_id":1,"location":[-0.63346,-0.60756,0.4],"orientation":[0.87042,-0.0,0.0,0.29372],"velocity":[4e-05,-2e-05,-1e-05],"angular_velocity":[0.00207,0.00189,-8e-05]},{"object_id":2,"location":[0.58381,1.3351,0.2],"orientation":[0.73912,-0.0,0.0,0.05186],"velocity":[5e-05,0.0001,-5e-05],"angular_velocity":[-0.0208,0.0069,-0.00047]}]},{"frame_id":79,"trajectory":[{"object_id":0,"location":[-1.58362,-0.85187,0.3],"orientation":[0.3697,-0.0,-0.0,0.72915],"velocity":[-0.00016,0.0001,-5e-05],"angular_velocity":[-0.01108,-0.01705,0.00044]},{"object_id":1,"location":[-0.63346,-0.60756,0.4],"orientation":[0.87042,-0.0,0.0,0.29372],"velocity":[4e-05,-2e-05,-1e-05],"angular_velocity":[0.00207,0.00189,-8e-05]},{"object_id":2,"location":[0.58381,1.3351,0.2],"orientation":[0.73912,-0.0,0.0,0.05186],"velocity":[5e-05,0.0001,-5e-05],"angular_velocity":[-0.0208,0.0069,-0.00047]}]},{"frame_id":80,"trajectory":[{"object_id":0,"location":[-1.58362,-0.85187,0.3],"orientation":[0.3697,-0.0,-0.0,0.72915],"velocity":[-0.00016,0.0001,-5e-05],"angular_velocity":[-0.01108,-0.01705,0.00044]},{"object_id":1,"location":[-0.63346,-0.60756,0.4],"orientation":[0.87042,-0.0,0.0,0.29372],"velocity":[4e-05,-2e-05,-1e-05],"angular_velocity":[0.00207,0.00189,-8e-05]},{"object_id":2,"location":[0.58381,1.3351,0.2],"orientation":[0.73912,-0.0,0.0,0.05186],"velocity":[5e-05,0.0001,-5e-05],"angular_velocity":[-0.0208,0.0069,-0.00047]}]},{"frame_id":81,"trajectory":[{"object_id":0,"location":[-1.58362,-0.85187,0.3],"orientation":[0.3697,-0.0,-0.0,0.72915],"velocity":[-0.00016,0.0001,-5e-05],"angular_velocity":[-0.01108,-0.01705,0.00044]},{"object_id":1,"location":[-0.63346,-0.60756,0.4],"orientation":[0.87042,-0.0,0.0,0.29372],"velocity":[4e-05,-2e-05,-1e-05],"angular_velocity":[0.00207,0.00189,-8e-05]},{"object_id":2,"location":[0.58381,1.3351,0.2],"orientation":[0.73912,-0.0,0.0,0.05186],"velocity":[5e-05,0.0001,-5e-05],"angular_velocity":[-0.0208,0.0069,-0.00047]}]},{"frame_id":82,"trajectory":[{"object_id":0,"location":[-1.58362,-0.85187,0.3],"orientation":[0.3697,-0.0,-0.0,0.72915],"velocity":[-0.00016,0.0001,-5e-05],"angular_velocity":[-0.01108,-0.01705,0.00044]},{"object_id":1,"location":[-0.63346,-0.60756,0.4],"orientation":[0.87042,-0.0,0.0,0.29372],"velocity":[4e-05,-2e-05,-1e-05],"angular_velocity":[0.00207,0.00189,-8e-05]},{"object_id":2,"location":[0.58381,1.3351,0.2],"orientation":[0.73912,-0.0,0.0,0.05186],"velocity":[5e-05,0.0001,-5e-05],"angular_velocity":[-0.0208,0.0069,-0.00047]}]},{"frame_id":83,"trajectory":[{"object_id":0,"location":[-1.58362,-0.85187,0.3],"orientation":[0.3697,-0.0,-0.0,0.72915],"velocity":[-0.00016,0.0001,-5e-05],"angular_velocity":[-0.01108,-0.01705,0.00044]},{"object_id":1,"location":[-0.63346,-0.60756,0.4],"orientation":[0.87042,-0.0,0.0,0.29372],"velocity":[4e-05,-2e-05,-1e-05],"angular_velocity":[0.00207,0.00189,-8e-05]},{"object_id":2,"location":[0.58381,1.3351,0.2],"orientation":[0.73912,-0.0,0.0,0.05186],"velocity":[5e-05,0.0001,-5e-05],"angular_velocity":[-0.0208,0.0069,-0.00047]}]},{"frame_id":84,"trajectory":[{"object_id":0,"location":[-1.58362,-0.85187,0.3],"orientation":[0.3697,-0.0,-0.0,0.72915],"velocity":[-0.00016,0.0001,-5e-05],"angular_velocity":[-0.01108,-0.01705,0.00044]},{"object_id":1,"location":[-0.63346,-0.60756,0.4],"orientation":[0.87042,-0.0,0.0,0.29372],"velocity":[4e-05,-2e-05,-1e-05],"angular_velocity":[0.00207,0.00189,-8e-05]},{"object_id":2,"location":[0.58381,1.3351,0.2],"orientation":[0.73912,-0.0,0.0,0.05186],"velocity":[5e-05,0.0001,-5e-05],"angular_velocity":[-0.0208,0.0069,-0.00047]}]},{"frame_id":85,"trajectory":[{"object_id":0,"location":[-1.58362,-0.85187,0.3],"orientation":[0.3697,-0.0,-0.0,0.72915],"velocity":[-0.00016,0.0001,-5e-05],"angular_velocity":[-0.01108,-0.01705,0.00044]},{"object_id":1,"location":[-0.63346,-0.60756,0.4],"orientation":[0.87042,-0.0,0.0,0.29372],"velocity":[4e-05,-2e-05,-1e-05],"angular_velocity":[0.00207,0.00189,-8e-05]},{"object_id":2,"location":[0.58381,1.3351,0.2],"orientation":[0.73912,-0.0,0.0,0.05186],"velocity":[5e-05,0.0001,-5e-05],"angular_velocity":[-0.0208,0.0069,-0.00047]}]},{"frame_id":86,"trajectory":[{"object_id":0,"location":[-1.58362,-0.85187,0.3],"orientation":[0.3697,-0.0,-0.0,0.72915],"velocity":[-0.00016,0.0001,-5e-05],"angular_velocity":[-0.01108,-0.01705,0.00044]},{"object_id":1,"location":[-0.63346,-0.60756,0.4],"orientation":[0.87042,-0.0,0.0,0.29372],"velocity":[4e-05,-2e-05,-1e-05],"angular_velocity":[0.00207,0.00189,-8e-05]},{"object_id":2,"location":[0.58381,1.3351,0.2],"orientation":[0.73912,-0.0,0.0,0.05186],"velocity":[5e-05,0.0001,-5e-05],"angular_velocity":[-0.0208,0.0069,-0.00047]}]},{"frame_id":87,"trajectory":[{"object_id":0,"location":[-1.58362,-0.85187,0.3],"orientation":[0.3697,-0.0,-0.0,0.72915],"velocity":[-0.00016,0.0001,-5e-05],"angular_velocity":[-0.01108,-0.01705,0.00044]},{"object_id":1,"location":[-0.63346,-0.60756,0.4],"orientation":[0.87042,-0.0,0.0,0.29372],"velocity":[4e-05,-2e-05,-1e-05],"angular_velocity":[0.00207,0.00189,-8e-05]},{"object_id":2,"location":[0.58381,1.3351,0.2],"orientation":[0.73912,-0.0,0.0,0.05186],"velocity":[5e-05,0.0001,-5e-05],"angular_velocity":[-0.0208,0.0069,-0.00047]}]},{"frame_id":88,"trajectory":[{"object_id":0,"location":[-1.58362,-0.85187,0.3],"orientation":[0.3697,-0.0,-0.0,0.72915],"velocity":[-0.00016,0.0001,-5e-05],"angular_velocity":[-0.01108,-0.01705,0.00044]},{"object_id":1,"location":[-0.63346,-0.60756,0.4],"orientation":[0.87042,-0.0,0.0,0.29372],"velocity":[4e-05,-2e-05,-1e-05],"angular_velocity":[0.00207,0.00189,-8e-05]},{"object_id":2,"location":[0.58381,1.3351,0.2],"orientation":[0.73912,-0.0,0.0,0.05186],"velocity":[5e-05,0.0001,-5e-05],"angular_velocity":[-0.0208,0.0069,-0.00047]}]},{"frame_id":89,"trajectory":[{"object_id":0,"location":[-1.58362,-0.85187,0.3],"orientation":[0.3697,-0.0,-0.0,0.72915],"velocity":[-0.00016,0.0001,-5e-05],"angular_velocity":[-0.01108,-0.01705,0.00044]},{"object_id":1,"location":[-0.63346,-0.60756,0.4],"orientation":[0.87042,-0.0,0.0,0.29372],"velocity":[4e-05,-2e-05,-1e-05],"angular_velocity":[0.00207,0.00189,-8e-05]},{"object_id":2,"location":[0.58381,1.3351,0.2],"orientation":[0.73912,-0.0,0.0,0.05186],"velocity":[5e-05,0.0001,-5e-05],"angular_velocity":[-0.0208,0.0069,-0.00047]}]}],"collision":[{"object_ids":[0,1],"frame_id":4,"location":[0.047984302043914795,0.041138216853141785,0.5999999642372131]},{"object_ids":[-1,0],"frame_id":16,"location":[-2.0,-0.4828813970088959,0.5999999046325684]},{"object_ids":[-1,2],"frame_id":20,"location":[0.22822275757789612,1.9999998807907104,0.40000009536743164]},{"object_ids":[0,1],"frame_id":21,"location":[-1.087399959564209,-0.5544448494911194,1.4901161193847656e-07]},{"object_ids":[-1,0],"frame_id":31,"location":[-2.0,-0.7010538578033447,0.5999999046325684]}]}